{
  "page_title": "طباعة كاميليون – متجر الطباعة الإلكتروني | طباعة الأقمشة، عروض الكرتون وألواح Honeycomb Board",
  "hero_title": "<span>كاميليون للطباعة</span><br>The Print Hub",
  "hero_desc": "ألواح Honeycomb Board، طباعة الأقمشة، مجسمات بالحجم الطبيعي، لافتات — صمم مجاناً عبر الإنترنت، شحن عالمي.",
  "wall_option_desc": "ابدأ التصميم المخصص",
  "search_placeholder": "ما المنتج الذي تبحث عنه اليوم؟",
  "search_guide": "ابحث عن المنتج الذي تحتاجه.",
  "search_guide_ex": "(مثال: لافتة، علم، كوب حراري، إلخ)",
  "search_no_result": "لم يتم العثور على نتائج.",
  "btn_search": "بحث",
  "btn_ai_advisor": "توصية AI للمنتجات",
  "btn_kapu_guide": "The Print Hub",
  "btn_product_search": "البحث عن المنتجات",
  "btn_signup_home": "التسجيل",
  "btn_bulk_order": "طلب بالجملة",
  "btn_kapu_sub": "إنتاج بنصف السعر · شحن مجاني · جودة استثنائية",
  "tab_all": "الكل",
  "tab_vector": "رسوم متجهة",
  "tab_graphic": "عناصر(PNG)",
  "tab_photo": "صور",
  "tab_pattern": "أنماط",
  "tab_logo": "شعارات(PNG)",
  "btn_my_library": "My page",
  "btn_cart": "🛒",
  "btn_add_to_cart": "🛒",
  "btn_purchase_top": "سلة",
  "purchase_choice_title": "كيف تريد الشراء؟",
  "purchase_current_product": "أضف إلى السلة بالمنتج الحالي",
  "purchase_new_material": "طباعة على مادة جديدة",
  "btn_login": "تسجيل الدخول",
  "btn_logout": "تسجيل الخروج",
  "wall_option_title": "ارتفاع الجدار",
  "tool_size_change": "📏 تغيير الحجم(مم)",
  "btn_save_cost": "تطبيق",
  "label_canvas_tools": "أدوات اللوحة",
  "btn_fit_screen": "ملاءمة الشاشة",
  "btn_lock": "قفل",
  "label_ai_tools": "أدوات الذكاء الاصطناعي",
  "btn_ai_gen": "مولّد الذكاء الاصطناعي",
  "btn_save_design": "💾 حفظ التصميم",
  "btn_logo_share": "مركز الشعارات",
  "label_basic_tools": "الأدوات الأساسية",
  "btn_add_text": "+ نص",
  "btn_font": "🅰️ الخطوط",
  "label_fill": "🎨 تعبئة",
  "label_stroke": "🖌️ حد",
  "label_shapes": "الأشكال",
  "label_upload": "رفع",
  "label_edit_layer": "تحرير والطبقات",
  "btn_undo": "تراجع",
  "btn_redo": "إعادة",
  "btn_copy": "نسخ",
  "btn_paste": "لصق",
  "btn_front": "إلى الأمام",
  "btn_back": "إلى الخلف",
  "btn_del": "حذف",
  "label_align": "محاذاة",
  "btn_center_all": "توسيط",
  "btn_full_bg": "تعيين كخلفية",
  "label_cut_shape": "خيارات القص",
  "msg_select_click": "حدد صورة وانقر",
  "btn_make_cutline": "إنشاء خط قص",
  "btn_keyring_hole": "فتحة سلسلة مفاتيح",
  "btn_stand_base": "قاعدة ستاند",
  "label_ai_image_tools": "أدوات صور الذكاء الاصطناعي",
  "btn_bg_remove": "(إزالة الخلفية)",
  "btn_enhance": "تحسين",
  "btn_text_outline": "حدود النص",
  "cart_title": "سلة التسوق",
  "label_payment_amt": "مبلغ الدفع",
  "label_product_price": "المجموع الفرعي",
  "label_option_price": "الخيارات",
  "label_grade_discount": "خصم العضوية",
  "label_total_price": "الإجمالي",
  "btn_do_checkout": "إتمام الشراء",
  "btn_print_quote": "طباعة عرض السعر",
  "label_material": "① المادة/السُمك",
  "label_finish": "② التشطيب",
  "label_addons": "③ إضافات",
  "label_opt_material": "المادة/السُمك",
  "label_opt_finish": "التشطيب",
  "label_opt_addon": "إضافات",
  "badge_required": "مطلوب",
  "badge_select": "اختر",
  "badge_optional": "اختياري",
  "label_qty": "الكمية",
  "label_quantity": "الكمية",
  "msg_select_option": "اختر الخيار",
  "label_user_design": "تصميم المستخدم",
  "msg_cart_empty": "سلة التسوق فارغة.",
  "msg_shipping_required": "يجب اختيار خيار الشحن.",
  "msg_load_design_confirm": "سيتم حذف التصميم الحالي. هل تريد تحميل التصميم السابق؟",
  "btn_re_edit": "إعادة التعديل",
  "msg_cart_added": "تمت إضافة المنتج إلى السلة.",
  "modal_login_title": "تسجيل الدخول",
  "placeholder_email": "البريد الإلكتروني",
  "placeholder_pw": "كلمة المرور",
  "btn_login_submit": "تسجيل الدخول",
  "msg_no_account": "ليس لديك حساب؟",
  "btn_signup": "إنشاء حساب",
  "btn_close": "إغلاق",
  "btn_confirm_date": "تأكيد التاريخ",
  "btn_confirm_time": "تأكيد الوقت",
  "modal_delivery_title": "📝 معلومات الشحن",
  "label_manager_name": "اسم جهة الاتصال",
  "label_contact_phone": "رقم الهاتف",
  "label_address": "العنوان",
  "label_request_memo": "تعليمات خاصة",
  "btn_payment_submit": "إنشاء الطلب والدفع",
  "btn_cancel": "إلغاء",
  "btn_documents": "المستندات",
  "doc_quotation": "عرض السعر",
  "doc_receipt": "إيصال",
  "doc_order_sheet": "أمر العمل",
  "doc_statement": "فاتورة",
  "modal_checkout_title": "تأكيد الطلب والدفع",
  "label_orderer_name": "مقدم الطلب",
  "label_shipping_addr": "عنوان الشحن",
  "btn_card_payment": "💳 بطاقة ائتمان / دفع سريع",
  "msg_bank_info": "[معلومات التحويل البنكي]",
  "msg_bank_name": "Community Federal Savings Bank",
  "msg_bank_account": "رقم الحساب: 8487335989 | ACH: 026073150 | SWIFT: CMFGUS33",
  "msg_bank_owner": "(صاحب الحساب: CHAMELEON PRINTING INC)",
  "msg_bank_note": "* يرجى تضمين رقم طلبك كمرجع للدفع. يتم تأكيد الطلبات عند استلام الدفع.",
  "btn_bank_confirm": "✅ لقد قمت بالتحويل (طلب التأكيد)",
  "btn_download_quote": "تحميل عرض السعر",
  "btn_download_work_sheet": "تحميل أمر العمل",
  "choice_modal_title": "🎨 اختر طريقة الإنشاء",
  "choice_modal_desc": "ابدأ التصميم باستخدام المحرر أو ارفع ملفاً جاهزاً.",
  "btn_design_direct": "التصميم بالمحرر",
  "btn_design_direct_sub": "استخدم القوالب والأدوات",
  "btn_order_file": "رفع ملف",
  "btn_order_file_sub": "رفع ملف PDF/AI",
  "modal_size_select_title": "ماذا تريد أن تصنع؟",
  "modal_calendar_title": "تاريخ التسليم المطلوب [مدة التنفيذ: 3 أيام]",
  "btn_rotate": "تدوير",
  "label_stroke_style": "📏 نمط الحد",
  "style_miter": "زاوية حادة",
  "style_round": "دائري",
  "label_opacity": "الشفافية",
  "modal_size_select_sub": "(اختر الحجم)",
  "modal_size_select_desc": "اختر حجماً لبدء التصميم.",
  "msg_loading": "جارٍ التحميل...",
  "btn_guide_on": "الأدلة",
  "help_text_shortcuts": "مسافة: تحريك / تمرير: تكبير / الأسهم: تحريك دقيق",
  "review_section_title": "✨ آراء العملاء",
  "review_section_desc": "اكتشف المشاريع الناجحة التي تم إنشاؤها مع طباعة كاميليون.",
  "rev_1_text": "\"نستخدمها في كل فعالية. لا يوجد شريك أفضل لوكالات الإعلان. ألواح Honeycomb Board بأسعار معقولة، ومدة التنفيذ سريعة، والجودة ممتازة.\"",
  "rev_1_user": "وكالة WPP — سارة ميتشل، نائبة الرئيس",
  "rev_2_text": "\"كنت أبحث عن قطعة رئيسية لفعاليتنا وأنا راضٍ تماماً. حتى لطلب قطعة واحدة، الشحن المجاني والخدمة اللطيفة كانا مثيرين للإعجاب!\"",
  "rev_2_user": "منظم الفعاليات مايك جونسون",
  "rev_3_text": "\"جودة سلاسل المفاتيح الأكريليك مذهلة. أسعار الجملة معقولة جداً مما يجعلهم أفضل شريك لموزعين مثلنا.\"",
  "rev_3_user": "صاحبة متجر هدايا — ليزا س.",
  "rev_4_text": "\"جودة طباعة الشيفون مذهلة. على عكس طباعة UV العادية، تبقى الألوان زاهية حتى بعد الغسيل. أنصح بها بشدة!\"",
  "rev_4_user": "متجر المصنوعات اليدوية — كارين م.",
  "rev_5_text": "\"وجهتنا الأولى لجميع فعالياتنا المؤسسية. سمعتهم كرقم 1 في ألواح Honeycomb Board مستحقة. المحرر عبر الإنترنت يجعل العملية سهلة جداً.\"",
  "rev_5_user": "أوجيلفي — المدير الإبداعي كريس تايلور",
  "rev_6_text": "\"الستاندات الورقية القابلة للتركيب السريع متينة بشكل مفاجئ. شكر خاص للفريق على المساعدة اللطيفة في التركيب.\"",
  "rev_6_user": "فريق تخطيط السوق",
  "rev_7_text": "\"جربت محررات إلكترونية متنوعة، لكن طباعة كاميليون تقدم أفضل توازن بين السعر والجودة بلا منازع.\"",
  "rev_7_user": "مبيعات كانون — ديفيد كيم",
  "rev_8_text": "\"لم أتوقع تشطيباً متيناً وجميلاً كهذا من مواد ورقية. أصبح الآن عنصراً أساسياً لمشاريعنا التسويقية.\"",
  "rev_8_user": "أدبوب للافتات",
  "rev_9_text": "\"تبدو أكثر فخامة من اللافتات العادية. الملمس الفريد والتخلص الصديق للبيئة مزايا كبيرة.\"",
  "rev_9_user": "المدير الإبداعي ريان بروكس",
  "footer_company_label": "الشركة :",
  "footer_company_value": "شركة كاميليون للطباعة المحدودة",
  "footer_ceo_label": "المدير التنفيذي :",
  "footer_ceo_value": "عبدالله الحربي",
  "footer_addr_label": "العنوان :",
  "footer_addr_value": "الرياض، حي العليا، طريق الملك فهد، برج المملكة، الطابق 22",
  "footer_biz_num_label": "السجل التجاري :",
  "footer_biz_num_value": "1010-587431",
  "footer_mail_order_label": "رقم الترخيص :",
  "footer_mail_order_value": "MC-2025-0047831",
  "footer_privacy_manager_label": "مسؤول الخصوصية :",
  "footer_privacy_manager_value": "محمد الشمري",
  "footer_cs_title": "مركز خدمة العملاء",
  "footer_cs_phone": "047-712-1148",
  "footer_cs_time": "الاثنين-الجمعة 09:00 ~ 18:00",
  "footer_cs_lunch": "استراحة الغداء 12:00 ~ 13:00",
  "footer_cs_closed": "* مغلق في عطلات نهاية الأسبوع والعطل الرسمية",
  "msg_deposit_complete": "تم طلب تأكيد الإيداع.\nانقر [إغلاق] لإعادة التعيين.",
  "msg_confirm_bank_transfer": "هل تريد المتابعة بالتحويل البنكي؟",
  "btn_confirm": "تأكيد",
  "pdf_quote_title": "ع ر ض   س ع ر",
  "pdf_order_sheet_title": "أمر العمل",
  "pdf_date": "التاريخ",
  "pdf_receiver": "إلى",
  "pdf_manager": "عناية",
  "pdf_total_amount": "المبلغ الإجمالي",
  "pdf_vat_include": "(شامل ضريبة القيمة المضافة)",
  "pdf_supplier": "المورد",
  "pdf_biz_num": "رقم السجل",
  "pdf_company_name": "الشركة",
  "pdf_ceo": "المدير التنفيذي",
  "pdf_addr": "العنوان",
  "pdf_contact": "الاتصال",
  "pdf_table_item": "الوصف",
  "pdf_table_qty": "الكمية",
  "pdf_table_price": "سعر الوحدة",
  "pdf_table_amount": "المبلغ",
  "pdf_total_sum": "المجموع الكلي",
  "pdf_delivery_date": "تاريخ التسليم",
  "pdf_shipping_addr": "عنوان الشحن",
  "pdf_request_memo": "ملاحظة",
  "pdf_delivery_manager": "مسؤول التسليم",
  "pdf_production_manager": "مسؤول الإنتاج",
  "pdf_product_label": "[المنتج",
  "pdf_option_none": "- بدون خيارات (قياسي)",
  "pdf_total_qty": "الكمية الإجمالية",
  "pdf_generated_by": "تم إنشاؤه بواسطة استوديو تصميم كاميليون",
  "pdf_statement_title": "كشف المعاملات",
  "pdf_receipt_title": "إيصال الدفع",
  "pdf_label_tax_id": "الرقم الضريبي / رقم تعريف صاحب العمل",
  "pdf_label_subtotal": "المجموع الفرعي",
  "pdf_label_tax": "ضريبة المبيعات",
  "pdf_footer_msg": "شكراً لتعاملكم معنا!",
  "msg_logout_confirm": "هل تريد تسجيل الخروج؟",
  "msg_login_required": "تسجيل الدخول مطلوب.",
  "msg_login_required_design": "تسجيل الدخول مطلوب لبدء التصميم.",
  "msg_template_apply_confirm": "تطبيق القالب على اللوحة الحالية؟\n(سيتم إضافته فوق تصميمك)",
  "msg_large_product_warning": "📢 المحرر سهل الاستخدام.\n\nأنشئ تصميمك الرائع.\nانقر على قالب للبدء.",
  "msg_processing_file": "جارٍ معالجة الملف...",
  "msg_unsupported_file": "صيغة ملف غير مدعومة.",
  "msg_pdf_loaded": "✅ تم تحميل ملف PDF بنجاح. (تم حفظ الأصل على الخادم)",
  "msg_select_image_for_outline": "يرجى تحديد صورة لإنشاء حدود خارجية!",
  "msg_generating": "جارٍ الإنشاء...",
  "msg_generating_docs": "جارٍ إنشاء المستندات...",
  "prompt_partner_name": "أدخل اسم الشركة (اسم المتجر)",
  "prompt_partner_phone": "أدخل رقم هاتف الاتصال",
  "prompt_partner_region": "أدخل المنطقة المطلوبة (مثال: لاس فيغاس، نيفادا)",
  "confirm_partner_apply": "[تأكيد الطلب]\nالاسم: {name}\nالهاتف: {phone}\nالمنطقة: {region}\n\nهل تريد تقديم هذا الطلب؟",
  "msg_partner_apply_success": "🎉 تم تقديم الطلب بنجاح!\nيمكنك استخدام ميزات الشريك بعد موافقة المسؤول.",
  "confirm_order_accept": "هل تريد قبول هذا الطلب؟",
  "msg_order_already_taken": "تم أخذ هذا الطلب بالفعل من قبل شريك آخر.",
  "msg_order_accept_success": "تم قبول الطلب! تحقق من علامة تبويب 'طلباتي'.",
  "alert_vip_info_needed": "يرجى إدخال اسم جهة الاتصال ورقم الهاتف.",
  "alert_vip_file_needed": "يرجى اختيار ملف واحد على الأقل للرفع.",
  "msg_uploading_files": "جارٍ رفع الملفات...",
  "msg_vip_order_success": "🎉 تم الإرسال بنجاح.\nالمستشار {manager} سيتواصل معك قريباً.",
  "alert_input_shipping": "يرجى إدخال جميع معلومات الشحن.",
  "msg_creating_order": "جارٍ إنشاء الطلب...",
  "msg_order_received": "تم استلام الطلب بنجاح.\nتم تطبيق خصم العضوية ({rate}%).",
  "btn_submit_complete": "اكتمل الإرسال",
  "confirm_bank_payment": "تقديم الطلب عبر التحويل البنكي؟\nيبدأ الإنتاج بعد تأكيد الدفع.",
  "msg_order_complete_bank": "اكتمل الطلب. يرجى التحويل إلى الحساب المحدد.",
  "alert_deposit_shortage": "رصيد الإيداع غير كافٍ.\n(النقص: {amount})",
  "confirm_deposit_pay": "الدفع باستخدام {amount} من رصيدك؟",
  "msg_processing_payment": "جارٍ معالجة الدفع...",
  "msg_payment_complete": "تم الدفع بنجاح!",
  "home_quick_badge": "كل ما تحتاجه للطباعة — بأقل الأسعار وأعلى جودة.",
  "home_quick_title": "اصنع تصاميم رائعة مع Chameleon.",
  "btn_manual_search": "البحث عن المنتجات يدوياً",
  "home_vip_title": "مركز استشارات ألواح Honeycomb Board للأكشاك",
  "home_vip_desc": "هل تجهّز كشك عرض أو متجراً مؤقتاً بألواح Honeycomb Board؟<br><strong>مستشار مخصص</strong> سيحلل احتياجاتك ويتواصل معك خلال 30 دقيقة.<br>مستشارك المخصص سيساعدك في إتمام الطلب بسهولة.",
  "home_btn_vip_upload": "رفع ملفات طلب VIP",
  "home_hotdeal_title": "ألواح Honeycomb Board",
  "home_hotdeal_desc": "ألواح خلية النحل المثالية لأجنحة المعارض والمتاجر المؤقتة والديكور الداخلي",
  "home_biz_title": "سوق أقمشة دبي",
  "home_biz_desc": "لافتات، مظلات، بانرات ومنتجات طباعة القماش المتنوعة",
  "home_print_title": "مطبعة الرياض",
  "home_print_desc": "منشورات، ملصقات، بطاقات عمل والمزيد من خدمات الطباعة",
  "home_goods_title": "متجر هدايا جدة",
  "home_goods_desc": "ميداليات، ملصقات، حقائب قماشية وهدايا مخصصة",
  "home_paper_display_title": "حوامل ورقية",
  "home_paper_display_desc": "حوامل عرض ورقية صديقة للبيئة للمتاجر والأرفف",
  "home_popular_title": "الأكثر مبيعاً",
  "home_popular_desc": "اكتشف منتجاتنا الأكثر شعبية",
  "menu_blog": "مدونة<br>كاميليون",
  "menu_review": "آراء<br>العملاء",
  "menu_promo": "إعلانات<br>محلية",
  "menu_trade": "تبادل<br>المعدات",
  "menu_job": "سوق<br>العمل",
  "menu_manual": "أدلة<br>المنتجات",
  "menu_orders": "تتبع الطلبات",
  "tier_main_title": "دليل <span>مزايا خصومات</span> العضوية",
  "tier_gold_name": "ذهبي",
  "tier_gold_discount": "خصم 3%",
  "tier_cond_1": "الشرط 1",
  "tier_cond_2": "الشرط 2",
  "tier_gold_cond_1": "إجمالي المشتريات <strong>10,000$+</strong>",
  "tier_gold_cond_2": "مشاركة <strong>10</strong> شعارات",
  "tier_plat_name": "بلاتيني",
  "tier_plat_discount": "خصم 5%",
  "tier_plat_cond_1": "إجمالي المشتريات <strong>20,000$+</strong>",
  "tier_plat_cond_2": "مشاركة <strong>100</strong> شعار",
  "tier_partner_name": "شريك",
  "tier_partner_discount": "خصم 10%",
  "tier_partner_cond_label": "الشرط",
  "tier_partner_cond_fee": "تقديم طلب شراكة",
  "tier_partner_cond_note": "(مطلوب رخصة تجارية)",
  "partner_banner_title": "سوق بعمولة منخفضة للبائعين<br><span style='color: #818cf8;'>مبيعات عالمية بأرباح عالية — اتركها لكاميليون!</span>",
  "partner_banner_desc": "فقط سجّل في كاميليون — نحن نتولى الشحن والإجراءات!<br>اعرض طباعة التيشيرتات والمنتجات المخصصة والمواد الترويجية والمزيد في سوق الطباعة بالجملة.<br><b style='color:#818cf8;'>أقل عمولة في السوق 6.5%</b> + الوصول إلى عملاء من شبكة طباعة رائدة عالمياً،<br>بالإضافة إلى <b style='color:#818cf8;'>البيع بضعف السعر في الأسواق العالمية</b>. احجز مكانك الآن!",
  "btn_partner_console": "الوصول إلى لوحة الشريك",
  "btn_partner_apply": "تقديم طلب شراكة",
  "contrib_title": "نظام المساهمين في كاميليون",
  "contrib_balance_label": "إجمالي أرباحي",
  "contrib_desc": "شارك موارد تصميمك واكسب مكافآت نقدية.<br>رفع صور منخفضة الجودة بشكل متكرر سيخفّض تقييمك. التقييم العالي يضاعف الأرباح x2، x4؛ التقييم المنخفض يقلل الأرباح للنصف.<br><span style='color:#ef4444; font-weight:bold;'>تحقق من الفئات!</span> سيتم إلغاء صلاحية الرفع إذا لم تتطابق الفئات أو تم تسجيل أقل من 3 كلمات مفتاحية.",
  "contrib_btn_png": "كائن PNG",
  "contrib_btn_svg": "كائن SVG",
  "contrib_btn_logo": "رفع شعار",
  "contrib_btn_template": "إنشاء قالب",
  "footer_menu_company": "من نحن",
  "footer_menu_notice": "إشعارات",
  "footer_menu_terms": "شروط الخدمة",
  "footer_menu_privacy": "سياسة الخصوصية",
  "//_COMMENT": "=== نصوص JS الديناميكية ===",
  "btn_guide_off": "إخفاء الأدلة",
  "msg_no_fonts": "لا توجد خطوط مسجلة.<br>يرجى تسجيل الخطوط في صفحة الإدارة.",
  "msg_select_text_font": "يرجى تحديد كائن نصي لتغيير الخط.",
  "msg_select_obj_outline": "يرجى تحديد كائن لتطبيق الحدود الخارجية.",
  "msg_select_obj_align": "يرجى تحديد كائن للمحاذاة.",
  "msg_select_file": "يرجى اختيار ملف.",
  "msg_upload_failed": "فشل الرفع: ",
  "msg_uploading": "جارٍ الرفع...",
  "tag_user_upload": "رفع المستخدم",
  "suffix_logo": " شعار",
  "confirm_unlock_all": "هل تريد إلغاء قفل جميع الكائنات المقفلة ({count})؟",
  "msg_select_obj_lock": "يرجى تحديد كائن لقفله.",
  "btn_lock_selection": "قفل التحديد",
  "btn_unlock_all": "إلغاء قفل الكل",
  "btn_lock_wizard": "معالج القفل",
  "prod_wall_1": "جدار قسم واحد",
  "prod_wall_2": "جدار قسمين",
  "prod_wall_3": "جدار 3 أقسام",
  "prod_wall_4": "جدار 4 أقسام",
  "prod_wall_5": "جدار 5 أقسام",
  "prod_banner_x": "لافتة X",
  "prod_award_board": "لوحة تكريم",
  "prod_photo_zone": "منطقة التصوير",
  "prod_fabric_wide": "قماش عريض",
  "prod_paper_stand": "ستاند ورقي",
  "msg_invalid_number": "يرجى إدخال رقم صحيح.",
  "msg_max_size_exceeded": "لا يمكن تجاوز الحجم الأقصى ({w}x{h} مم).",
  "msg_size_rotated": "تم تدوير الأبعاد لتناسب اللوحة.",
  "msg_data_loading": "جارٍ تحميل البيانات...",
  "msg_db_disconnected": "قاعدة البيانات غير متصلة",
  "msg_no_data": "لا توجد بيانات لعرضها.",
  "btn_go_back": "العودة إلى الصفحة السابقة",
  "msg_load_failed": "فشل تحميل البيانات.",
  "btn_retry": "إعادة المحاولة",
  "btn_apply_now": "تقديم الآن",
  "btn_prev_page": "السابق",
  "btn_next_page": "التالي",
  "label_page": "صفحة",
  "msg_select_template": "يرجى اختيار قالب.",
  "msg_click_select": "انقر لاختيار الملفات",
  "msg_drag_drop": "أو اسحب الملفات وأفلتها هنا",
  "ph_common_tags": "مثال: سامسونج، شعار، بسيط",
  "ph_enter_tags": "أدخل الكلمات المفتاحية المشتركة",
  "default_title": "بدون عنوان",
  "msg_enter_title": "يرجى إدخال عنوان.",
  "msg_design_registered": "🎉 تم تسجيل التصميم! (+500 نقطة مكتسبة)\nتحقق منه في علامة تبويب [القوالب].",
  "msg_files_selected": "تم تحديد {count} ملفات.",
  "msg_click_to_upload": "انقر رفع لتسجيل الكل.",
  "msg_upload_success": "نجاح!",
  "msg_bg_remove_server": "إزالة الخلفية تتطلب الاتصال بالخادم.",
  "msg_select_image": "يرجى تحديد صورة.",
  "msg_pdf_error": "يرجى رفع ملفات PDF في خطوة 'الطلب'. المحرر يدعم الصور فقط.",
  "//_COMMENT_2": "=== نصوص مفقودة مضافة ===",
  "confirm_apply_bg": "تطبيق تصميم الخلفية هذا؟\n(سيتم استبدال الخلفية الحالية)",
  "confirm_bg_remove": "هل تريد إزالة الخلفية؟",
  "confirm_upscale": "هل تريد مضاعفة الدقة باستخدام الذكاء الاصطناعي؟",
  "msg_input_desc": "يرجى إدخال وصف.",
  "msg_gen_fail": "فشل الإنشاء",
  "msg_min_page_limit": "مطلوب صفحة واحدة على الأقل.",
  "btn_my_page": "📂 صفحتي",
  "msg_generating_quote": "جارٍ إنشاء عرض السعر...",
  "err_quote_gen_failed": "فشل إنشاء عرض السعر.",
  "err_quote_error": "خطأ في إنشاء عرض السعر: ",
  "btn_complete_order": "إتمام الطلب",
  "btn_pay_now": "ادفع الآن",
  "msg_processing_design": "جارٍ معالجة التصميم...",
  "default_design_name": "تصميمي",
  "msg_uploading_file": "جارٍ رفع الملف...",
  "msg_file_added_to_cart": "تمت إضافة طلب الملف إلى السلة.",
  "msg_failed": "فشل: ",
  "msg_generating_order_sheet": "جارٍ إنشاء أمر العمل...",
  "msg_converting_design": "جارٍ تحويل التصميم",
  "msg_mileage_limit_exceeded": "يمكن استخدام النقاط بحد أقصى 5% من مبلغ الشراء: ",
  "msg_saving": "جارٍ الحفظ...",
  "msg_generating_print_pdf": "جارٍ إنشاء ملف PDF للطباعة...",
  "msg_design_saved": "✅ تم حفظ التصميم!",
  "msg_save_failed": "فشل الحفظ: ",
  "msg_voice_new_order": "تم استلام طلب جديد.",
  "confirm_withdraw_request": "تقديم طلب سحب؟\n(المعلومات غير الصحيحة قد تؤخر الإيداع.)",
  "msg_sending": "جارٍ الإرسال...",
  "msg_withdraw_success": "تم تقديم طلب السحب.\nالإيداع خلال 5 أيام بعد مراجعة المسؤول.",
  "msg_clipboard_empty": "الحافظة فارغة.",
  "mp_menu_dashboard": "لوحة التحكم",
  "mp_menu_designs": "تصاميمي",
  "mp_menu_sales": "معروض للبيع",
  "mp_menu_orders": "الطلبات",
  "mp_menu_profit": "الأرباح والنقاط",
  "mp_welcome_title": "مرحباً!",
  "mp_welcome_desc": "أنشئ تصاميم مذهلة اليوم.",
  "btn_back_to_editor": "العودة إلى المحرر",
  "mp_label_mileage": "نقاطي",
  "mp_label_total_spend": "إجمالي الإنفاق",
  "mp_label_logo_count": "الشعارات المشاركة",
  "mp_label_active_orders": "الطلبات النشطة",
  "mp_welcome_user": "مرحباً، {name}!",
  "confirm_load_design": "تحميل هذا التصميم في المحرر؟",
  "confirm_delete": "هل أنت متأكد من الحذف؟",
  "default_customer": "عميل",
  "msg_canvas_not_ready": "اللوحة غير جاهزة.",
  "err_canvas_not_ready": "لم يتم تحميل اللوحة بالكامل. يرجى الانتظار.",
  "msg_no_locked_bg": "لم يتم العثور على خلفية مقفلة.",
  "msg_bg_unlocked": "تم إلغاء قفل الخلفية.",
  "msg_bg_locked": "تم قفل الخلفية.",
  "ctx_undo": "تراجع",
  "ctx_redo": "إعادة",
  "ctx_copy": "نسخ",
  "ctx_paste": "لصق",
  "ctx_delete": "حذف",
  "ctx_front": "إحضار للأمام",
  "ctx_back": "إرسال للخلف",
  "ctx_lock": "قفل",
  "ctx_unlock": "إلغاء القفل",
  "ctx_unlock_all": "إلغاء قفل الكل",
  "btn_google_login": "المتابعة مع Google",
  "btn_apple_login": "المتابعة مع Apple",
  "placeholder_pw_confirm": "تأكيد كلمة المرور",
  "label_select_manager": "اختر مستشاراً (اختياري)",
  "partner_menu_pool": "الطلبات المتاحة",
  "partner_menu_my": "عروضي",
  "partner_menu_reviews": "التقييمات/المراجعات",
  "partner_title_pool": "📍 طلبات محلية متاحة (مجمع الطلبات)",
  "msg_loading_orders": "جارٍ تحميل الطلبات...",
  "btn_write_post": "✏️ كتابة منشور",
  "th_date": "التاريخ",
  "th_product": "المنتج",
  "th_amount": "المبلغ",
  "th_status": "الحالة",
  "th_action": "الإجراء",
  "mp_recent_logs": "📢 سجلات الأرباح الأخيرة",
  "mp_saved_designs": "📂 التصاميم المحفوظة",
  "msg_wait_moment": "يرجى الانتظار لحظة.",
  "confirm_select_partner": "مشاركة رقمك ({myPhone}) مع الشريك\nوتأكيد هذا الاختيار؟",
  "msg_review_saved": "تم حفظ المراجعة بنجاح!",
  "msg_no_partner_auth": "لم يتم العثور على صلاحية شريك.",
  "msg_post_deleted": "تم حذف هذا المنشور.",
  "msg_processing": "جارٍ المعالجة...",
  "btn_admin_logout": "تسجيل خروج المسؤول",
  "confirm_admin_logout": "هل أنت متأكد من تسجيل الخروج من حساب المسؤول؟",
  "confirm_logout": "هل أنت متأكد من تسجيل الخروج؟",
  "modal_signup_title": "إنشاء حساب",
  "btn_signup_submit": "تسجيل",
  "msg_have_account": "لديك حساب بالفعل؟",
  "btn_to_login": "تسجيل الدخول",
  "btn_to_signup": "إنشاء حساب",
  "err_input_required": "يرجى ملء جميع الحقول.",
  "err_db_connection": "خطأ في الاتصال بقاعدة البيانات.",
  "err_pw_mismatch": "كلمات المرور غير متطابقة.",
  "err_pw_length": "يجب أن تكون كلمة المرور 6 أحرف على الأقل.",
  "msg_signup_success": "اكتمل التسجيل!",
  "msg_login_success": "تم تسجيل الدخول!",
  "msg_verify_email": "تم إرسال بريد التحقق. يرجى مراجعة صندوق الوارد.",
  "err_prefix": "خطأ: ",
  "err_login_fail": "فشل تسجيل الدخول: ",
  "alert_mileage_shortage": "رصيد النقاط غير كافٍ.",
  "alert_input_depositor": "يرجى إدخال اسم المودع.",
  "msg_outline_failed": "تعذر إنشاء حدود متجهة لهذه الصورة.",
  "msg_image_load_failed": "فشل تحميل الصورة.",
  "vip_fast_inquiry": "⚡ استفسار سريع",
  "vip_manager_intro": "\"مستشارونا المخصصون سيردون بسرعة عبر الهاتف\"",
  "vip_manager_jisuk": "المدير أليكس",
  "vip_manager_eunmi": "المديرة سارة",
  "vip_manager_sunhee": "المدير جيمس",
  "vip_inquiry_time": "ساعات العمل: الاثنين-الجمعة، 9 صباحاً - 6 مساءً",
  "gen_prod_unit_price": "سعر الوحدة",
  "gen_prod_quantity": "الكمية",
  "gen_prod_total": "المبلغ الإجمالي",
  "btn_add_cart": "🛒 أضف إلى السلة",
  "msg_added_to_cart": "تمت الإضافة إلى السلة!",
  "msg_added_to_cart_desc": "تمت إضافة المنتج المحدد إلى سلة التسوق.",
  "btn_go_to_payment": "💳 إتمام الشراء الآن",
  "btn_continue_shopping": "🛍️ متابعة التسوق",
  "vip_manager_1_name": "المدير أليكس",
  "vip_manager_1_phone": "+1-234-345-1946",
  "vip_manager_2_name": "المديرة سارة",
  "vip_manager_2_phone": "+1-234-779-5393",
  "vip_manager_3_name": "المدير جيمس",
  "vip_manager_3_phone": "+1-234-349-3328",
  "btn_prev": "السابق",
  "btn_next": "التالي",
  "label_page_suffix": "صفحة",
  "search_placeholder_start": "ما التصميم الذي تبحث عنه؟ (مثال: قطة، محيط، سماء)",
  "//_COMMENT_3": "=== واجهة المحرر ===",
  "editor_size": "الحجم",
  "editor_char_spacing": "التباعد",
  "editor_line_height": "الارتفاع",
  "editor_bg_color": "لون الخلفية",
  "editor_basic_palette": "لوحة الألوان الأساسية",
  "editor_recommended": "🎨 موصى به",
  "editor_tab_template": "القوالب",
  "editor_tab_element": "العناصر",
  "ph_search_template": "بحث (مثال: مقهى، تخفيضات)",
  "editor_design_wizard": "معالج التصميم",
  "editor_unlock_bg": "إلغاء قفل الخلفية",
  "editor_stroke_width": "عرض الحد",
  "editor_text_edit": "تحرير النص",
  "editor_lock_selection": "قفل التحديد",
  "btn_mobile_template": "🎨 القوالب",
  "//_COMMENT_4": "=== أزرار معالج التصميم ===",
  "wiz_flyer": "منشور إعلاني",
  "wiz_poster": "ملصق",
  "wiz_card": "بطاقة",
  "wiz_menu": "قائمة طعام",
  "wiz_banner_h": "لافتة أفقية",
  "wiz_banner_v": "لافتة عمودية",
  "wiz_insta_panel": "منشور إنستغرام",
  "//_COMMENT_5": "=== خيارات الأدلة ===",
  "guide_off": "🚫 إيقاف",
  "guide_cross": "✚ تقاطع",
  "guide_3col": "3 أعمدة",
  "guide_4col": "4 أعمدة",
  "guide_5col": "5 أعمدة",
  "guide_grid": "▦ شبكة",
  "//_COMMENT_6": "=== نوافذ القوالب ===",
  "tpl_load_title": "🎨 تحميل قالب",
  "tpl_load_desc": "لديك تصميم قيد التنفيذ.\nكيف تريد تطبيق القالب المحدد؟",
  "tpl_action_add": "إضافة للحالي",
  "tpl_action_add_desc": "تراكب على التصميم الحالي",
  "tpl_action_replace": "بدء جديد",
  "tpl_action_replace_desc": "مسح الحالي والاستبدال",
  "btn_cancel_back": "إلغاء والعودة",
  "size_select_title": "📏 ما الحجم الذي تريده؟",
  "size_select_desc": "سيتم ضبط القالب تلقائياً ليناسب حجم المنتج المحدد.",
  "btn_apply_template": "تطبيق القالب المحدد",
  "search_label": "بحث",
  "ph_search_input": "بحث...",
  "tpl_obj_label": "🧩 العناصر",
  "tpl_search_product": "البحث عن منتجات للقالب",
  "//_COMMENT_7": "=== مولّد الذكاء الاصطناعي ===",
  "ai_title": "✨ مولّد صور الذكاء الاصطناعي",
  "ai_prompt_label": "الوصف (الأمر)",
  "ph_ai_prompt": "مثال: أرنب بني لطيف يجلس في غابة",
  "btn_generate": "إنشاء",
  "ai_waiting": "في انتظار النتيجة",
  "btn_add_to_canvas": "إضافة إلى اللوحة",
  "//_COMMENT_8": "=== نافذة إتمام الطلب ===",
  "msg_order_complete_title": "🎉 اكتمل الطلب!",
  "btn_download_order_sheet": "📄 تحميل أمر العمل",
  "btn_download_quotation": "📑 تحميل عرض السعر",
  "//_COMMENT_9": "=== نافذة بيع التصميم ===",
  "sell_title": "💎 مشاركة/بيع التصميم",
  "sell_benefit_1": "اكسب <span class='highlight'>100 نقطة</span> فوراً، <span class='highlight'>200 نقطة</span> لكل استخدام",
  "sell_benefit_2": "سحب نقدي من <span class='highlight'>10$</span>",
  "sell_benefit_3": "دخل سلبي يومي من مشاركة التصاميم!",
  "sell_type_label": "نوع القالب",
  "sell_type_vector": "متجه",
  "sell_type_image": "صورة",
  "sell_keyword_label": "الكلمات المفتاحية والعنوان",
  "ph_sell_title": "مثال: فعالية عيادة، ملصق صيفي",
  "btn_register": "تسجيل",
  "modal_font_title": "اختيار الخط",
  "//_COMMENT_10": "=== نافذة الاختيار ===",
  "btn_purchase": "شراء",
  "btn_purchase_sub": "رفع الملفات عبر السلة",
  "btn_detail_page": "عرض التفاصيل",
  "btn_story_page": "عرض القصة",
  "//_COMMENT_11": "=== نافذة إنشاء القالب ===",
  "tpl_create_title": "بدء إنشاء القالب",
  "tpl_create_desc": "سجّل تصميمك واكسب الإيرادات!",
  "tpl_create_tip_1": "📷 <strong>متجه/صورة:</strong> سجّل كمتجه إذا كانت الخلفية متجهة، وكصورة إذا كانت صورة.",
  "tpl_create_tip_2": "💡 <strong>نصيحة:</strong> ضع النص أولاً، ثم بدّل الخلفيات للتسجيل السريع.",
  "tpl_create_tip_3": "💰 <strong>أرباح أكثر:</strong> كلمات مفتاحية أكثر = ظهور أكثر = أرباح أكثر.",
  "tpl_create_tip_4": "⚡ <strong>مكافأة فورية:</strong> اكسب عند الرفع + إيرادات مبيعات مستمرة.",
  "tpl_create_size_label": "📏 حجم القالب (مم)",
  "ph_width": "العرض",
  "ph_height": "الارتفاع",
  "btn_start_design": "🚀 ابدأ التصميم",
  "//_COMMENT_12": "=== محرر الجوال ===",
  "btn_delete_obj": "حذف",
  "btn_done_edit": "تم",
  "ph_text_input": "أدخل النص هنا...",
  "//_COMMENT_13": "=== تنبيهات JS الديناميكية (main.js) ===",
  "msg_product_info_missing": "⚠️ معلومات المنتج غير موجودة لهذا التصميم.\nيرجى إعادة اختيار مواصفات المنتج.",
  "msg_cannot_load_form": "تعذر تحميل نموذج الطلب.",
  "confirm_status_change": "تغيير الحالة إلى '{status}'؟",
  "msg_min_withdraw": "الحد الأدنى لمبلغ السحب هو 20$.",
  "msg_input_real_name": "يرجى إدخال اسم صاحب الحساب.",
  "msg_input_phone": "يرجى إدخال رقم هاتفك.",
  "msg_input_id_number": "يرجى إدخال رقم الهوية بشكل صحيح.",
  "msg_input_bank_info": "يرجى إدخال معلومات حسابك البنكي.",
  "confirm_purchase_final": "تأكيد الشراء؟ (لا يُسمح بالإرجاع)",
  "msg_purchase_confirmed": "تم تأكيد الشراء. شكراً لك!",
  "msg_input_search_keyword": "يرجى إدخال كلمات البحث.",
  "msg_select_thumb_svg": "يرجى اختيار كل من الصورة المصغرة وملف SVG.",
  "msg_file_already_uploaded": "تم رفع هذا الملف بالفعل: {name}\n(يتم التخطي لتجنب التكرار)",
  "msg_upload_complete_points": "🎉 اكتمل الرفع! تم اكتساب {amount} نقطة.",
  "msg_image_too_large": "ملف الصورة كبير جداً. (الحالي: {size} ميغابايت)\nالحد الأقصى لحجم الملف هو 1 ميغابايت.",
  "msg_admin_only_sell": "فقط المسؤولون يمكنهم تسجيل التصاميم للبيع.",
  "msg_no_permission": "تعذر التحقق من الصلاحيات.",
  "msg_partner_fields_required": "اسم الشركة ورقم الهاتف والمنطقة مطلوبة.",
  "msg_partner_applied": "✅ تم تقديم طلب الشراكة.\nسيتم تغيير رتبتك إلى 'شريك' بعد موافقة المسؤول.",
  "confirm_cancel_form": "إلغاء وإغلاق النموذج؟",
  "msg_invalid_size": "يرجى إدخال حجم صالح.",
  "msg_editor_load_error": "خطأ في تحميل المحرر. يرجى تحديث الصفحة.",
  "confirm_go_editor": "الانتقال إلى محرر التصميم؟",
  "msg_submit_error": "خطأ في الإرسال: ",
  "msg_apply_error": "خطأ في الطلب: ",
  "//_COMMENT_PARTNER_MODAL": "=== نافذة طلب الشراكة ===",
  "partner_apply_title": "🤝 طلب شراكة (وكالة معتمدة)",
  "partner_apply_desc": "كن وكيلاً إقليمياً للطباعة والإعلان واكسب الأرباح.",
  "partner_label_company": "اسم الشركة",
  "partner_ph_company": "مثال: تصميم كاميليون",
  "partner_label_phone": "رقم الاتصال",
  "partner_ph_phone": "+1-234-567-8900",
  "partner_label_region": "منطقة الخدمة (يمكن إدخال عدة مناطق)",
  "partner_ph_region": "مثال: نيويورك، لوس أنجلوس، شيكاغو (مفصولة بفواصل)",
  "partner_region_hint": "* للمناطق المتعددة، افصل بفواصل.",
  "partner_label_items": "المنتجات الرئيسية (للمصنعين)",
  "partner_ph_items": "مثال: لافتات، أكريليك، لوحات (الوكالات تدخل 'تخطيط/تصميم')",
  "partner_btn_apply": "تقديم الطلب",
  "partner_btn_cancel": "سحب الطلب",
  "partner_btn_close": "إغلاق",
  "//_COMMENT_14": "=== لوحة تحكم الشريك ===",
  "partner_console_title": "لوحة تحكم الشريك",
  "partner_region_unset": "المنطقة غير محددة",
  "partner_tab_pool": "الطلبات المباشرة",
  "partner_tab_my_orders": "طلباتي",
  "partner_tab_settlement": "التسوية",
  "partner_pool_title": "📍 الطلبات المباشرة (أولوية القبول)",
  "btn_refresh": "تحديث",
  "partner_my_orders_title": "📋 طلباتي النشطة",
  "msg_no_history": "لا توجد سجلات",
  "partner_withdraw_label": "متاح للسحب (بعد خصم الرسوم)",
  "partner_pending_label": "سحب معلق (مطلوب)",
  "btn_withdraw": "💸 طلب سحب",
  "partner_settlement_title": "تفاصيل التسوية",
  "th_date_col": "التاريخ",
  "th_order_amount": "مبلغ الطلب",
  "th_settled_amount": "المبلغ المسوّى",
  "th_status_col": "الحالة",
  "my_order_tracking_title": "📦 تتبع الطلب",
  "msg_loading_text": "جارٍ التحميل...",
  "//_COMMENT_15": "=== صفحة السلة والدفع ===",
  "cart_upload_guide": "ارفع ملفات التصميم الخاصة بك هنا",
  "btn_bulk_upload": "رفع ملفات بالجملة",
  "label_mileage_use": "Ⓜ️ استخدام نقاط المكافآت",
  "label_mileage_owned": "الرصيد:",
  "btn_max": "الحد الأقصى",
  "msg_mileage_5pct": "* حتى 5% من مبلغ الدفع",
  "label_available_limit": "الحد المتاح:",
  "label_final_pay_amount": "إجمالي الدفع",
  "label_pay_method": "طريقة الدفع",
  "label_card_pay": "💳 بطاقة / دفع سريع (فوري)",
  "label_bank_transfer": "🏦 تحويل بنكي (الإنتاج بعد التأكيد)",
  "label_deposit_use": "💰 استخدام رصيدي الائتماني",
  "label_balance": "الرصيد",
  "label_balance_loading": "(جارٍ التحقق من الرصيد...)",
  "btn_do_final_pay": "ادفع الآن",
  "label_estimate_price": "السعر التقديري (للوحدة)",
  "estimate_note_1": "* قد يكون السعر النهائي أقل مع خصومات النقاط والعضوية.",
  "estimate_note_2": "تحقق من السعر النهائي في سلة التسوق.",
  "rv_title": "آراء العملاء",
  "rv_write": "كتابة مراجعة",
  "rv_login_required": "سجّل الدخول لكتابة مراجعة",
  "rv_placeholder": "شارك تجربتك الصادقة مع هذا المنتج",
  "rv_submit": "إرسال المراجعة",
  "rv_photo_add": "إضافة صورة",
  "rv_load_more": "تحميل المزيد",
  "rv_no_reviews": "لا توجد مراجعات بعد. كن أول من يشارك!",
  "rv_total_reviews": "مراجعات",
  "rv_avg_rating": "متوسط التقييم",
  "rv_submitted": "تم إرسال المراجعة!",
  "//_COMMENT_PARTNER": "=== ترجمة لوحة تحكم الشريك ===",
  "pt_no_pool_orders": "لا توجد طلبات متاحة حالياً.",
  "pt_no_my_orders": "لا توجد طلبات قيد التنفيذ.",
  "pt_no_product_info": "لا توجد معلومات منتج",
  "pt_no_attachments": "لا توجد مرفقات",
  "pt_btn_accept": "قبول الطلب",
  "pt_min_ago": " دقيقة مضت",
  "pt_taken_by_other": "تم قبوله من شريك آخر",
  "pt_accepted": "مقبول",
  "pt_my_accepted": "قبلته أنا",
  "pt_status_confirmed": "مؤكد (بانتظار التسوية)",
  "pt_status_shipping": "قيد الشحن (بانتظار التسليم)",
  "pt_btn_ship": "شحن الآن",
  "pt_order_suffix": "طلب",
  "pt_no_settlement": "لا توجد سجلات تسوية متاحة.",
  "pt_withdrawable": "قابل للسحب",
  "pt_badge_franchise": "وكالة معتمدة",
  "pt_badge_admin": "مسؤول (رئيسي)",
  "pt_badge_partner": "شريك",
  "pt_no_access": "🚫 تم رفض الوصول.\n\nيرجى انتظار موافقة المسؤول.",
  "pt_tab_products": "منتجاتي",
  "pt_tab_register": "تسجيل منتج",
  "pt_tab_orders": "إدارة الطلبات",
  "pt_tab_settlement": "التسوية",
  "pt_tab_guide": "الدليل",
  "pt_register_submit": "تقديم للمراجعة",
  "pt_product_pending": "قيد المراجعة",
  "pt_product_approved": "معروض للبيع",
  "pt_product_rejected": "مرفوض",
  "pt_no_products": "لم يتم تسجيل منتجات بعد.",
  "pt_stock": "المخزون",
  "pt_select_category": "اختر الفئة",
  "pt_category": "الفئة *",
  "pt_product_name_kr": "اسم المنتج (كوري) *",
  "pt_product_name_jp": "اسم المنتج (ياباني)",
  "pt_product_name_en": "اسم المنتج (إنجليزي)",
  "pt_price_krw": "السعر (وون كوري) *",
  "pt_price_jpy": "السعر (¥)",
  "pt_price_usd": "السعر ($)",
  "pt_product_image": "صورة المنتج *",
  "pt_click_upload": "انقر لرفع الصورة",
  "pt_description_kr": "الوصف (كوري) *",
  "pt_description_jp": "الوصف (ياباني)",
  "pt_description_en": "الوصف (إنجليزي)",
  "pt_shipping_info": "معلومات الشحن",
  "pt_register_success": "تم تقديم المنتج للمراجعة. ستبدأ المبيعات بعد موافقة المسؤول.",
  "pt_err_category": "يرجى اختيار فئة.",
  "pt_err_name": "يرجى إدخال اسم المنتج.",
  "pt_err_price": "يرجى إدخال السعر.",
  "pt_err_image": "يرجى اختيار صورة المنتج.",
  "pt_no_orders": "لا توجد طلبات بعد.",
  "pt_ship_now": "شحن الآن",
  "pt_confirm_ship": "تحديد كمشحون؟",
  "pt_ship_success": "تم التحديد كمشحون.",
  "pt_eligible_amount": "المبلغ القابل للسحب",
  "pt_waiting_amount": "قيد الانتظار (15 يوماً)",
  "pt_requested_amount": "طلب سحب مقدم",
  "pt_commission_notice": "العمولة: بطاقة 3.4% + مبيعات 6.6% = 10% إجمالي يُخصم قبل الدفع.",
  "pt_15day_notice": "السحب متاح بعد 15 يوماً من تأكيد العميل للاستلام.",
  "pt_btn_withdraw": "طلب سحب",
  "pt_no_eligible": "لا يوجد مبلغ قابل للسحب.",
  "pt_status_requested": "طلب سحب مقدم",
  "pt_status_pending_confirm": "بانتظار التأكيد",
  "pt_withdraw_title": "طلب سحب",
  "pt_wd_amount": "المبلغ",
  "pt_wd_bank": "معلومات البنك (البنك + رقم الحساب) *",
  "pt_wd_holder": "صاحب الحساب *",
  "pt_wd_tax_invoice": "فاتورة ضريبية (مطلوبة) *",
  "pt_wd_submit": "تقديم",
  "pt_wd_success": "تم تقديم طلب السحب. الإيداع بعد مراجعة المسؤول.",
  "pt_err_bank": "يرجى إدخال معلومات البنك.",
  "pt_err_holder": "يرجى إدخال اسم صاحب الحساب.",
  "pt_err_tax": "يرجى إرفاق الفاتورة الضريبية.",
  "pt_guide_fee_title": "معلومات العمولة",
  "pt_guide_fee_1": "رسوم الدفع بالبطاقة: 3.4%",
  "pt_guide_fee_2": "عمولة المبيعات: 6.6%",
  "pt_guide_fee_3": "<strong>الإجمالي: 10%</strong> (يُخصم من مبلغ الطلب)",
  "pt_guide_settle_title": "التسوية والإيداع",
  "pt_guide_settle_1": "السحب متاح بعد <strong>15 يوماً</strong> من تأكيد العميل للاستلام.",
  "pt_guide_settle_2": "يجب إرفاق <strong>فاتورة ضريبية</strong> لطلب السحب.",
  "pt_guide_settle_3": "الإيداع خلال <strong>5 أيام عمل</strong> بعد مراجعة المسؤول.",
  "pt_guide_flow_title": "مسار المبيعات",
  "pt_guide_flow_1": "تقديم المنتج للمراجعة (الشريك)",
  "pt_guide_flow_2": "موافقة المسؤول ← عرض المنتج في المتجر",
  "pt_guide_flow_3": "طلب العميل ← التحقق في علامة تبويب إدارة الطلبات",
  "pt_guide_flow_4": "التحديد كمشحون",
  "pt_guide_flow_5": "تأكيد العميل للاستلام ← انتظار 15 يوماً",
  "pt_guide_flow_6": "طلب سحب + إرفاق فاتورة ضريبية ← الإيداع",
  "//_COMMENT_PT_PAGE": "=== صفحة الشريك (partner.html) ===",
  "pt_btn_home": "العودة إلى الرئيسية",
  "pt_btn_logout": "تسجيل الخروج",
  "pt_btn_translate": "ترجمة تلقائية",
  "pt_btn_edit": "تعديل",
  "pt_btn_delete": "حذف",
  "pt_btn_cancel": "إلغاء",
  "pt_label_name": "اسم المنتج <span style='color:#ef4444;'>*</span>",
  "pt_label_price": "السعر <span style='color:#ef4444;'>*</span>",
  "pt_label_stock": "كمية المخزون <span class='required'>*</span>",
  "pt_label_desc": "وصف المنتج",
  "pt_image_hint": "مربع (1:1) موصى به / حد أقصى 5 ميغابايت",
  "pt_shipping_placeholder": "مثال: الشحن خلال 3-5 أيام عمل",
  "pt_first_register": "سجّل منتجك الأول",
  "pt_reject_reason": "سبب الرفض",
  "pt_edit_coming_soon": "ميزة التعديل قريباً. يرجى الحذف وإعادة التسجيل.",
  "pt_confirm_delete": "حذف هذا المنتج؟",
  "pt_err_name_first": "يرجى إدخال اسم المنتج أولاً.",
  "pt_err_desc_first": "يرجى إدخال وصف المنتج أولاً.",
  "pt_translate_fail": "فشلت الترجمة. يرجى الإدخال يدوياً.",
  "pt_recipient": "المستلم",
  "pt_contact": "الاتصال",
  "pt_order_amount": "مبلغ الطلب",
  "pt_rate_us": "السعر: $1 = ₩2,000 = ¥200",
  "pt_rate_jp": "السعر: 100¥ = ₩2,000 = $2",
  "pt_commission_notice_full": "<strong>محلي:</strong> بطاقة 3.4% + مبيعات 6.6% = 10% إجمالي يُخصم &nbsp;|&nbsp; السحب متاح بعد 15 يوماً من تأكيد التسليم",
  "pt_overseas_notice": "<strong>دولي:</strong> جمارك + شحن دولي 20% إضافي (محلي 10% + دولي 20% = 30% إجمالي)",
  "pt_th_date": "التاريخ",
  "pt_th_product_code": "رمز المنتج",
  "pt_th_order_amount": "مبلغ الطلب",
  "pt_th_commission": "العمولة",
  "pt_th_settlement": "المبلغ الصافي",
  "pt_th_status": "الحالة",
  "pt_guide_fee_overseas": "<strong>دولي:</strong> محلي 10% + جمارك/شحن 20% = <strong>إجمالي 30%</strong>",
  "pt_guide_global_title": "التسعير الدولي",
  "pt_guide_global_kr": "<strong>الشركاء الكوريون:</strong> ₩1,000 ← ¥200 / $2 دولياً",
  "pt_guide_global_jp": "<strong>الشركاء اليابانيون:</strong> ¥100 ← ₩2,000 / $2 دولياً",
  "pt_guide_global_us": "<strong>الشركاء الأمريكيون:</strong> $1 ← ₩2,000 / ¥200 دولياً",
  "pt_guide_global_margin": "هامش ربح تقريبي <strong>مضاعف</strong> على المبيعات الدولية!",
  "pt_wd_bank_ph": "مثال: Chase Bank 123-456-789",
  "pt_wd_holder_ph": "جون سميث",
  "mp_sales_title": "🎨 التصاميم المعروضة للبيع (قوالبي)",
  "mp_sales_total": "الأرباح المقدرة",
  "mp_sales_guide": "<i class='fa-solid fa-circle-info'></i> اكسب <b>100 نقطة</b> للقوالب، <b>150 نقطة</b> للشعارات المرفوعة فوراً.<br>اكسب <b>200 نقطة</b> إضافية في كل مرة يشتري مستخدم آخر تصميمك.",
  "mp_deposit_title": "💰 الرصيد (قابل للسحب)",
  "mp_deposit_desc": "إيرادات المبيعات والأرصدة المشحونة مجمعة.",
  "mp_btn_withdraw": "💸 سحب",
  "mp_btn_charge": "💳 شحن الرصيد",
  "mp_charge_notice": "يرجى التحويل إلى حساب المسؤول والتواصل مع خدمة العملاء.",
  "mp_mileage_title": "Ⓜ️ نقاط المكافآت",
  "mp_mileage_desc": "مكتسبة من الفعاليات والأنشطة (قابلة للاستخدام عند الدفع)",
  "mp_mileage_notice": "💡 النقاط غير قابلة للسحب النقدي.<br>يمكن استخدام حتى <strong>10%</strong> من قيمة كل عملية شراء.",
  "mp_wallet_log_title": "📊 سجل المعاملات",
  "mp_th_datetime": "التاريخ",
  "mp_th_type": "النوع",
  "mp_th_desc": "الوصف",
  "mp_th_amount": "المبلغ",
  "mp_no_records": "لم يتم العثور على سجلات.",
  "mp_wd_title": "💸 طلب سحب",
  "mp_wd_notice": "اسحب رصيدك كنقد.<br><strong>الحد الأدنى للسحب: 20$</strong>",
  "mp_wd_amount": "مبلغ السحب",
  "mp_wd_amount_ph": "أدخل 20$ أو أكثر",
  "mp_wd_balance": "الرصيد",
  "mp_wd_bank": "اسم البنك",
  "mp_wd_account": "رقم الحساب",
  "mp_wd_account_ph": "أدخل بدون شرطات",
  "mp_wd_holder": "صاحب الحساب",
  "mp_wd_phone": "رقم الهاتف",
  "mp_wd_rrn": "الرقم الضريبي (للتقارير الضريبية)",
  "mp_wd_submit": "تقديم",
  "mp_wd_cancel": "إلغاء",
  "mp_order_history": "📦 الطلبات / التوصيل",
  "mp_min_withdraw_notice": "الحد الأدنى للسحب: 20$",
  "msg_insufficient_deposit": "الرصيد غير كافٍ.",
  "msg_enter_bank_info": "يرجى إدخال اسم البنك ورقم الحساب واسم صاحب الحساب.",
  "msg_enter_contact_id": "يرجى إدخال رقم الهاتف والرقم الضريبي.",
  "label_deposit": "إيداع",
  "label_payment": "دفع",
  "label_withdrawal": "سحب",
  "label_admin_adjust": "تعديل المسؤول",
  "label_other": "أخرى",
  "contrib_upload_title": "📤 رفع",
  "contrib_upload_png": "رفع كائن PNG",
  "contrib_upload_svg": "رفع متجه SVG",
  "contrib_upload_logo": "رفع شعار",
  "contrib_label_tags": "كلمات البحث (الوسوم)",
  "contrib_ph_tags": "يتم الملء تلقائياً عند اختيار ملف.",
  "contrib_label_thumb": "1. صورة مصغرة (JPG/PNG)",
  "contrib_label_svg": "2. ملف SVG الأصلي",
  "contrib_label_file": "اختر ملفاً",
  "contrib_file_tip": "* يُوصى بملفات PNG شفافة.",
  "contrib_btn_submit": "رفع واكسب النقاط",
  "contrib_btn_cancel": "إلغاء",
  "//_COMMENT_MYPAGE_ORDERS": "=== طلبات صفحتي ===",
  "btn_reorder": "إعادة الطلب",
  "btn_cancel_order": "إلغاء الطلب",
  "btn_write_review": "كتابة مراجعة",
  "msg_review_completed": "اكتملت المراجعة",
  "msg_no_orders": "لا يوجد سجل طلبات.",
  "msg_no_product_info": "لا توجد معلومات منتج",
  "label_product": "المنتج",
  "label_more_items": "المزيد",
  "confirm_cancel_order": "إلغاء هذا الطلب؟",
  "confirm_cancel_refund": "هل تريد إلغاء الطلب واسترداد المبلغ؟",
  "msg_refund_processing": "جارٍ معالجة الاسترداد...",
  "msg_refund_complete": "تم الاسترداد بنجاح.",
  "msg_refund_failed": "فشل الاسترداد. يرجى التواصل مع خدمة العملاء.",
  "msg_bank_cancel_notice": "طلبات التحويل البنكي تتطلب عملية استرداد منفصلة.",
  "label_refund_done": "تم الاسترداد",
  "btn_cancel_refund": "إلغاء واسترداد",
  "confirm_reorder": "إضافة هذه العناصر إلى السلة مرة أخرى؟",
  "confirm_go_to_cart": "الانتقال إلى السلة؟",
  "msg_no_bids_yet": "لم يتم تلقي عروض بعد.\nالشركاء يراجعون. يرجى الانتظار.",
  "msg_no_sales": "لا توجد تصاميم معروضة للبيع.",
  "msg_no_reviews": "لا توجد مراجعات بعد.",
  "label_partner_reviews": "مراجعات الشركاء",
  "msg_selection_complete": "اكتمل الاختيار",
  "msg_contact_partner": "اتصل بهذا الرقم لترتيب موعد.",
  "btn_select_partner": "اختيار هذا الشريك",
  "msg_received_bids": "العروض المستلمة",
  "msg_compare_bids": "قارن الأسعار والتقييمات لاختيار شريك.",
  "btn_view_reviews": "عرض المراجعات",
  "prompt_enter_phone": "أدخل رقم هاتفك لمشاركته مع الشريك:",
  "msg_phone_required": "رقم الهاتف مطلوب للتواصل مع الشريك.",
  "msg_matching_complete": "اكتمل التوافق!\nمعلومات اتصال الشريك متاحة الآن.",
  "prompt_enter_rating": "أدخل تقييم الشريك (1-5):",
  "prompt_enter_review": "اترك مراجعة للعملاء الآخرين:",
  "default_review": "خدمة ممتازة وعمل عالي الجودة.",
  "msg_no_matched_partner": "لم يتم العثور على شريك متوافق.",
  "msg_new_bid_notification": "قدم شريك عرضاً. يرجى مراجعة عروض الأسعار.",
  "msg_untitled": "بدون عنوان",
  "msg_penalty_applied": "تم تطبيق عقوبة",
  "msg_registration_reward": "مكافأة التسجيل",
  "msg_no_recent_revenue": "لا توجد إيرادات في آخر 30 يوماً.",
  "msg_penalty_notice_title": "إشعار عقوبة الحساب",
  "msg_penalty_notice_body": "تم وضع حسابك تحت <b>حالة العقوبة</b>.<br>خلال هذه الفترة، تقتصر إيرادات المبيعات على <b>50 نقطة لكل تسجيل</b>.",
  "label_reason": "السبب",
  "//_COMMENT_ORDER_STATUS": "=== حالة الطلب ===",
  "status_접수대기": "قيد الانتظار",
  "status_입금대기": "بانتظار الدفع",
  "status_접수됨": "مقبول",
  "status_제작준비": "قيد التحضير",
  "status_제작중": "قيد الإنتاج",
  "status_배송중": "قيد الشحن",
  "status_배송완료": "تم التسليم",
  "status_구매확정": "مؤكد",
  "status_완료됨": "مكتمل",
  "status_취소됨": "ملغي",
  "status_임시작성": "مسودة",
  "vip_form_title": "طلب استشارة ألواح Honeycomb Board للأكشاك",
  "vip_form_desc": "اختر مستشاراً مخصصاً وارفع ملفاتك.",
  "vip_form_name": "اسم جهة الاتصال",
  "vip_form_name_ph": "مثال: أحمد محمد",
  "vip_form_phone": "رقم الهاتف",
  "vip_form_memo": "ملاحظات الطلب",
  "vip_form_memo_ph": "اكتب تفاصيل طلب عرض الأسعار أو تعليمات العمل.",
  "vip_form_file": "تحميل الملفات (اختيار متعدد)",
  "vip_form_file_click": "انقر هنا لاختيار الملفات (يمكن اختيار عدة ملفات)",
  "vip_form_submit": "إرسال",
  "vip_form_mgr1": "المدير Sarah",
  "vip_form_mgr2": "المدير Alex",
  "vip_form_mgr3": "المدير James",
  "vip_form_mgr4": "جهة اتصال المقر",
  "//_SIDEBAR_MENU": "--- قائمة الشريط الجانبي ---",
  "menu_template": "القوالب",
  "menu_element": "العناصر",
  "menu_text": "النص",
  "menu_upload": "رفع",
  "menu_ai": "AI",
  "menu_cutout": "القص",
  "menu_save": "حفظ",
  "menu_size": "الحجم",
  "menu_align": "محاذاة",
  "menu_page": "PAGE",
  "//_SIDEBAR_PANELS": "--- لوحات جانبية ---",
  "panel_shapes_colors": "الأشكال والألوان",
  "panel_text": "النص",
  "panel_ai": "AI",
  "panel_cutout": "القص والتأثيرات",
  "panel_save": "حفظ وتصدير",
  "panel_page": "إدارة الصفحات",
  "panel_size": "📏 الحجم والقماش",
  "panel_align": "محاذاة والطبقات",
  "label_background": "الخلفية",
  "label_recent_elements": "العناصر المستخدمة مؤخراً",
  "label_none_yet": "لا يوجد بعد",
  "label_my_uploads": "📁 تحميلاتي",
  "label_login_required": "متاح بعد تسجيل الدخول",
  "label_ai_desc": "أنشئ صوراً بالذكاء الاصطناعي.<br>أدخل النص لإنشاء تلقائي.",
  "label_cut_section": "القص",
  "label_free_download": "تحميل مجاني",
  "label_canvas_control": "التحكم بالقماش",
  "label_align_artboard": "محاذاة للوح",
  "label_layer_order": "ترتيب الطبقات",
  "label_object_rotate": "تدوير الكائن",
  "btn_text_effect": "✨ تأثير النص",
  "btn_png": "تحميل PNG",
  "btn_pdf": "تحميل PDF",
  "btn_add_page": "إضافة صفحة",
  "btn_del_page": "حذف الصفحة الحالية",
  "btn_bg_lock": "قفل/فتح الخلفية",
  "align_left": "يسار",
  "align_center": "وسط",
  "align_right": "يمين",
  "align_top": "أعلى",
  "align_middle": "وسط",
  "align_bottom": "أسفل",
  "//_DSM_MODAL": "--- بدء التصميم ---",
  "dsm_btn_start": "البحث عن المنتجات",
  "dsm_title": "ماذا تريد أن تصنع؟",
  "dsm_subtitle": "اختر التنسيق لفتح المحرر.",
  "dsm_digital": "أونلاين · رقمي",
  "dsm_thumbnail": "صورة مصغرة",
  "dsm_webposter": "ملصق ويب",
  "dsm_cardnews": "بطاقة إخبارية",
  "dsm_detailpage": "صفحة التفاصيل",
  "dsm_shorts": "شورتس",
  "dsm_video": "فيديو",
  "dsm_ppt": "عرض تقديمي",
  "dsm_gifmaker": "صانع GIF",
  "dsm_print": "مطبوعات",
  "dsm_h_banner": "لافتة أفقية",
  "dsm_v_banner": "لافتة عمودية",
  "dsm_custom_input": "✏️ إدخال مخصص (mm)",
  "dsm_custom_hint": "إذا كنت تحتاج فقط إلى تصميم بحجم مخصص دون اختيار منتج، أدخل الحجم هنا",
  "dsm_ph_w": "العرض",
  "dsm_ph_h": "الارتفاع",
  "dsm_start": "ابدأ",
  "dsm_back": "رجوع",
  "dsm_ph_search": "ابحث عما تريد إنشاءه!",
  "editor_tab_text_tpl": "قوالب النص",
  "label_clipart": "قصاصات فنية · عناصر",
  "ph_search_clipart": "البحث عن قصاصات فنية",
  "sc_title": "حاسبة الشحن بالذكاء الاصطناعي",
  "sc_desc": "أدخل مدينتك وحجم المنتج، وسيوصي الذكاء الاصطناعي بأفضل طريقة شحن",
  "sc_ph_city": "اسم مدينة التسليم",
  "sc_prod_general": "مطبوعات عامة",
  "sc_prod_honeycomb": "لوح Honeycomb Board",
  "sc_prod_fabric": "قماش / نسيج",
  "sc_prod_acrylic": "أكريليك / فوماكس",
  "sc_btn_calc": "حساب تكلفة الشحن",
  "sc_alert_city": "يرجى إدخال اسم المدينة",
  "sc_calculating": "جاري الحساب...",
  "sc_disclaimer": "هذا تقدير أولي للاسترشاد فقط. يرجى التواصل عبر الدردشة للحصول على عرض سعر دقيق.",
  "sc_btn_chat": "تواصل معنا",
  "sc_btn_open": "حاسبة الشحن",
  "sc_partners": "تعمل طباعة كاميليون مع 560 شريكاً في أكثر من 20 دولة حول العالم.",
  "sc_banner_title": "نشحن إلى كل مدينة في العالم.<br>احصل على عرض سعر الآن.",
  "sc_banner_desc": "ألواح Honeycomb Board معيارية ومسطحة لتقليل الحجم.",
  "sc_chat_btn": "دردشة الشحن العالمي",
  "msg_min_order_notice": "تم تطبيق الحد الأدنى للطلب ﷼20.",
  "msg_min_order_applied": "تم تطبيق الحد الأدنى للطلب ﷼20.",
  "label_delivery_area": "منطقة التوصيل",
  "desc_delivery_area_global": "ألواح Honeycomb Board لها رسوم شحن إضافية خارج المدن الرئيسية.",
  "opt_metro_area_global": "منطقة حضرية رئيسية",
  "opt_non_metro_area_global": "مناطق أخرى",
  "msg_non_metro_fee_global": "سيتم تطبيق رسوم شحن إضافية للمناطق غير الحضرية.",
  "label_non_metro_shipping": "رسوم شحن إضافية",
  "sub_title": "مزايا حصرية بـ ﷼115 شهرياً فقط",
  "sub_desc": "<span style=\"color:#fbbf24;\">خصم 10% على الطلبات</span> + قوالب بريميوم غير محدودة + <span style=\"color:#fbbf24;\">رصيد يساوي قيمة الاشتراك</span>",
  "sub_monthly": "اشتراك شهري",
  "sub_annual": "اشتراك سنوي",
  "sub_monthly_period": "دفع شهري",
  "sub_annual_period": "دفع سنوي",
  "sub_lifetime": "اشتراك مدى الحياة",
  "sub_lifetime_period": "دفعة واحدة، استخدام مدى الحياة",
  "sub_save": "خصم 50%",
  "sub_benefit": "خصم 10% على المنتجات + ميزات مميزة غير محدودة",
  "sub_ft1": "ميزات مميزة غير محدودة",
  "sub_ft2": "خصم 10% على المنتجات",
  "sub_btn": "اشترك الآن",
  "sub_active": "اشتراك PRO الخاص بك نشط",
  "sub_feat_templates": "قوالب مميزة غير محدودة",
  "sub_feat_discount": "خصم 10% على جميع المنتجات",
  "sub_feat_priority": "أولوية في الإنتاج",
  "sub_premium_lock": "قالب مميز",
  "sub_premium_msg": "اشترك في PRO لاستخدام جميع القوالب المميزة",
  "sub_success_msg": "تم تفعيل اشتراك PRO الخاص بك! 🎉",
  "sub_manage_title": "إدارة",
  "sub_manage_desc": "تغيير الدفع · إلغاء الاشتراك",
  "sub_cancel_info": "يمكنك الإلغاء في أي وقت بسهولة.<br>يستمر الوصول حتى نهاية الفترة",
  "sub_manage_btn": "إدارة الاشتراك",
  "sub_no_subscription": "لا يوجد اشتراك نشط. يرجى الاشتراك أولاً.",
  "sub_cancel_btn": "إلغاء الاشتراك",
  "sub_cancel_confirm": "هل أنت متأكد من إلغاء اشتراكك؟\nيمكنك الاستمرار في استخدام الخدمة حتى نهاية فترة الاشتراك الحالية.",
  "ve_clip_required": "يرجى إضافة مقطع أولاً",
  "ve_audio_none": "لا يوجد صوت",
  "ve_audio_no_result": "لم يتم العثور على صوت",
  "ve_audio_loading": "جاري التحميل...",
  "ve_audio_fail": "فشل التحميل",
  "ve_audio_label": "الصوت",
  "ve_audio_no_conn": "لا يوجد اتصال بقاعدة البيانات",
  "ve_audio_prev": "السابق",
  "ve_audio_next": "التالي",
  "img_tool_edit": "تحرير",
  "img_tool_bg_remove": "إزالة الخلفية",
  "img_tool_eraser": "ممحاة",
  "eraser_undo": "تراجع",
  "eraser_cancel": "إلغاء",
  "eraser_done": "تم",
  "wizard_btn": "معالج التصميم AI",
  "wizard_title": "معالج التصميم",
  "wizard_desc": "اكتب كلمة واحدة. سيقوم الذكاء الاصطناعي بالتصميم بالصور والمحتوى المناسب.",
  "wizard_label_title": "اكتب كلمة",
  "wizard_placeholder": "مثال: مقهى، سحاب، بحر، صيف، عيد ميلاد",
  "wizard_label_style": "النمط",
  "wizard_generate": "إنشاء التصميم",
  "wizard_step_bg": "جاري البحث عن الخلفية...",
  "wizard_step_title": "جاري وضع العنوان...",
  "wizard_step_desc": "جاري إنشاء الوصف...",
  "wizard_step_elements": "جاري إضافة عناصر التصميم...",
  "wizard_step_shapes": "جاري إضافة الأشكال الزخرفية...",
  "wizard_step_stickers": "جاري وضع الملصقات...",
  "wizard_content_hint": "أدخل المحتوى هنا",
  "wizard_style_blue": "أزرق",
  "wizard_style_yellow": "أصفر",
  "wizard_style_candy": "حلوى",
  "wizard_style_dark": "داكن",
  "referral_title": "رمز الإحالة",
  "referral_desc": "أدخل بريد المُحيل لمنحه 10% من مبلغ الشراء كرصيد.",
  "referral_placeholder": "بريد المُحيل الإلكتروني",
  "referral_verify": "تحقق",
  "referral_verified": "تم التحقق من المُحيل!",
  "referral_not_found": "البريد غير موجود.",
  "referral_self_error": "لا يمكنك إحالة نفسك.",
  "referral_no_refund": "تم احتساب مكافأة الإحالة! شكراً لك!",
  "referral_no_refund_short": "هذا الطلب غير قابل للاسترداد بعد مكافأة الإحالة.",
  "referral_applied": "تم تطبيق المُحيل",
  "referral_badge": "إحالة",
  "referral_log_info": "سيتم خصم ضريبة الاستقطاع المطبقة عند السحب.",
  "referral_log_desc": "تم إيداع رصيد من خلال إحالة {name}.",
  "label_order_num": "طلب",
  "btn_delete_selected": "حذف المحدد",
  "confirm_delete_uploads": "هل تريد حذف الصور المحددة؟",
  "msg_delete_failed": "فشل الحذف.",
  "menu_theme": "سمة",
  "panel_theme": "🎨 سمة الألوان",
  "theme_desc": "تغيير نغمة ألوان اللوحة بالكامل.",
  "theme_custom": "لون مخصص",
  "theme_tint": "تلوين",
  "theme_shift": "تحويل اللون",
  "theme_intensity": "الشدة",
  "theme_reset": "استعادة الألوان الأصلية",
  "theme_warm": "غروب دافئ",
  "theme_ocean": "محيط بارد",
  "theme_forest": "غابة",
  "theme_purple": "بنفسجي ملكي",
  "theme_pink": "وردي",
  "theme_golden": "ذهبي",
  "theme_mono": "أحادي اللون",
  "theme_sepia": "بني عتيق",
  "ve_ai_composer": "مؤلف موسيقي بالذكاء الاصطناعي",
  "ve_ai_composer_desc": "إنشاء موسيقى مع غناء وكلمات",
  "ve_ai_music_placeholder": "مثال) موسيقى مقهى مبهجة ومرحة مع بيانو وجيتار",
  "ve_ai_music_style": "النمط",
  "ve_ai_music_lyrics": "كلمات الأغنية",
  "ve_ai_music_lyrics_hint": "حد أقصى 400 حرف، اختياري",
  "ve_ai_music_lyrics_placeholder": "[verse]\nاكتب كلمات الأغنية هنا...\n\n[chorus]\nكلمات اللازمة هنا...",
  "ve_ai_music_generate": "إنشاء الموسيقى",
  "ve_ai_music_my_list": "موسيقاي",
  "ve_ai_music_loading": "جاري تحميل موسيقاك...",
  "ve_ai_music_no_db": "يتطلب اتصال بقاعدة البيانات",
  "ve_ai_music_login": "يرجى تسجيل الدخول أولاً",
  "ve_ai_music_need_input": "أدخل وصفاً أو اختر نمطاً",
  "ve_ai_music_starting": "جاري بدء التأليف بالذكاء الاصطناعي...",
  "ve_ai_music_requesting": "جاري إرسال الطلب...",
  "ve_ai_music_composing": "جاري التأليف...",
  "ve_ai_music_queue": "في قائمة الانتظار...",
  "ve_ai_music_saving": "جاري الحفظ...",
  "ve_ai_music_done": "تم إنشاء الموسيقى بالذكاء الاصطناعي!",
  "ve_ai_music_fail": "فشل التأليف بالذكاء الاصطناعي",
  "ve_ai_music_play_fail": "فشل التشغيل",
  "ve_ai_music_delete_confirm": "حذف هذه الموسيقى؟",
  "ve_sec": "ث",
  "ve_style_pop": "بوب",
  "ve_style_cinematic": "سينمائي",
  "ve_style_jazz": "جاز",
  "ve_style_acoustic": "أكوستيك",
  "ve_style_classical": "كلاسيكي",
  "ve_style_hiphop": "هيب هوب",
  "ve_format_landscape": "أفقي",
  "ve_format_portrait": "عمودي/شورتس",
  "ve_format_square": "مربع",
  "ve_music_none": "بدون",
  "ve_music_none_desc": "بدون موسيقى",
  "ve_trans_none": "بدون",
  "ve_trans_fade": "تلاشي",
  "ve_trans_slide_l": "← انزلاق",
  "ve_trans_slide_r": "→ انزلاق",
  "ve_trans_slide_up": "↑ انزلاق",
  "ve_trans_zoom_in": "تكبير",
  "ve_trans_zoom_out": "تصغير",
  "ve_trans_wipe": "مسح",
  "ve_trans_slide_down": "↓ انزلاق",
  "ve_trans_flip": "قلب",
  "ve_trans_spin": "دوران",
  "ve_trans_blur": "ضبابية",
  "ve_trans_cross_zoom": "تكبير متقاطع",
  "ve_trans_split": "تقسيم",
  "ve_tpl_title_card": "بطاقة عنوان",
  "ve_tpl_enter_title": "أدخل العنوان",
  "ve_tpl_subtitle": "عنوان فرعي",
  "ve_tpl_lower_third": "شريط سفلي",
  "ve_tpl_name": "الاسم",
  "ve_tpl_job_title": "المسمى الوظيفي",
  "ve_tpl_caption": "تعليق",
  "ve_tpl_caption_text": "نص التعليق",
  "ve_tpl_quote": "اقتباس",
  "ve_tpl_enter_quote": "\"أدخل اقتباساً هنا\"",
  "ve_tpl_author": "— المؤلف",
  "ve_tpl_announce": "إعلان",
  "ve_tpl_important": "إشعار مهم",
  "ve_tpl_details": "التفاصيل",
  "ve_tpl_intro": "مقدمة",
  "ve_tpl_channel": "اسم القناة",
  "ve_tpl_video_title": "أدخل عنوان الفيديو",
  "ve_tpl_outro": "خاتمة",
  "ve_tpl_thanks": "شكراً للمشاهدة",
  "ve_tpl_like_sub": "👍 إعجاب واشتراك",
  "ve_tpl_see_next": "نراكم في المرة القادمة!",
  "ve_tpl_countdown": "عد تنازلي",
  "ve_tpl_starting_soon": "يبدأ قريباً",
  "ve_tpl_subscribe_btn": "زر الاشتراك",
  "ve_tpl_subscribe": "🔔 اشتراك",
  "ve_tpl_progress": "التقدم",
  "ve_tpl_complete_pct": "40% مكتمل",
  "ve_add_clip": "إضافة صور أو فيديوهات",
  "ve_click_to_add": "انقر للإضافة",
  "ve_text": "نص",
  "ve_add_text": "إضافة نص إلى اللوحة",
  "ve_text_edit": "تعديل النص",
  "ve_content": "المحتوى",
  "ve_size": "الحجم",
  "ve_color": "اللون",
  "ve_bold": "غامق",
  "ve_shadow": "ظل",
  "ve_outline": "حدود",
  "ve_bg_box": "مربع الخلفية",
  "ve_font": "الخط",
  "ve_delete": "حذف",
  "ve_layer": "الطبقات",
  "ve_shapes": "الأشكال",
  "ve_rect": "مستطيل",
  "ve_circle": "دائرة",
  "ve_sticker": "ملصقات",
  "ve_place_sticker": "وضع الملصق على اللوحة",
  "ve_img_library": "مكتبة الصور",
  "ve_search": "بحث...",
  "ve_loading": "جاري التحميل...",
  "ve_load_more": "تحميل المزيد",
  "ve_no_db": "لا يوجد اتصال بقاعدة البيانات",
  "ve_load_fail": "فشل التحميل",
  "ve_no_images": "لا توجد صور",
  "ve_no_more_images": "لا مزيد من الصور",
  "ve_element_added": "تمت إضافة عنصر الصورة",
  "ve_img_templates": "قوالب الصور",
  "ve_img_tpl_desc": "إدراج صور المحرر كطبقات",
  "ve_img_tpl_added": "تمت إضافة قالب الصورة",
  "ve_transitions": "الانتقالات",
  "ve_scene_time": "مدة المشهد",
  "ve_speed_normal": "عادي",
  "ve_play_speed": "سرعة التشغيل",
  "ve_select_clip": "اختر مقطعاً",
  "ve_img_adjust": "تعديلات الصورة",
  "ve_brightness": "السطوع",
  "ve_contrast": "التباين",
  "ve_saturation": "التشبع",
  "ve_blur_label": "ضبابية",
  "ve_hue": "درجة اللون",
  "ve_reset": "إعادة تعيين",
  "ve_templates": "القوالب",
  "ve_apply_to_scene": "تطبيق على المشهد الحالي",
  "ve_export_presets": "إعدادات التصدير",
  "ve_presentation": "عرض تقديمي",
  "ve_current": "الحالي",
  "ve_save_project": "حفظ المشروع",
  "ve_project_name": "اسم المشروع",
  "ve_project": "مشروع",
  "ve_save": "حفظ",
  "ve_saved_projects": "المشاريع المحفوظة",
  "ve_no_saved": "لا توجد مشاريع محفوظة",
  "ve_load": "تحميل",
  "ve_saving": "جاري الحفظ...",
  "ve_saved": "تم الحفظ",
  "ve_saved_thumb": "تم الحفظ (صورة مصغرة)",
  "ve_save_fail_quota": "فشل الحفظ: التخزين ممتلئ",
  "ve_save_fail": "فشل الحفظ",
  "ve_overwrite_confirm": "استبدال المشروع الحالي؟",
  "ve_loaded": "تم التحميل",
  "ve_delete_confirm": "تأكيد الحذف؟",
  "ve_selected_element": "العنصر المحدد",
  "ve_type": "النوع",
  "ve_width": "العرض",
  "ve_height": "الارتفاع",
  "ve_fill": "التعبئة",
  "ve_radius": "نصف القطر",
  "ve_rotation": "الدوران",
  "ve_start": "البداية",
  "ve_end": "النهاية",
  "ve_sec_unit": "ث",
  "ve_clip_props": "خصائص المقطع",
  "ve_video": "فيديو",
  "ve_image": "صورة",
  "ve_time": "المدة",
  "ve_transition": "الانتقال",
  "ve_position": "الموضع",
  "ve_adjust": "التعديلات",
  "ve_audio_select": "اختر الموسيقى من علامة تبويب الصوت",
  "ve_canvas_click": "انقر على اللوحة للوضع",
  "ve_copied": "تم النسخ",
  "ve_no_clipboard": "لم يتم نسخ شيء",
  "ve_pasted": "تم اللصق",
  "ve_deleted": "تم الحذف",
  "ve_preset_applied": "تم تطبيق الإعداد",
  "ve_paused": "متوقف مؤقتاً — قم بالتعديل على اللوحة",
  "ve_element_deleted": "تم حذف العنصر",
  "ve_default_text": "نص",
  "ve_duplicate": "تكرار",
  "ve_img_clip_needed": "اختر مقطع صورة",
  "ve_db_required": "يتطلب اتصال بقاعدة البيانات",
  "ve_prompt_motion": "أدخل وصفاً للحركة",
  "ve_no_original": "لا تتوفر صورة أصلية",
  "ve_restored": "تمت الاستعادة إلى الأصل",
  "ve_editor_title": "محرر الفيديو",
  "gm_max_frames": "يمكن رفع 10 إطارات كحد أقصى.",
  "gm_max_frames_partial": "حد أقصى 10 إطارات!",
  "gm_frames_added": " إطار سيتم إضافتها.",
  "gm_frame": "إطار",
  "gm_delete": "حذف",
  "gm_text": "نص",
  "gm_no_db": "لا يوجد اتصال بقاعدة البيانات",
  "gm_load_fail": "فشل التحميل",
  "gm_no_images": "لا توجد صور",
  "gm_no_elements": "لا توجد عناصر",
  "gm_need_2_frames": "يرجى إضافة إطارين على الأقل.",
  "gm_need_frames": "يرجى إضافة إطارات.",
  "gm_preparing": "جاري تحضير GIF...",
  "gm_rendering": "جاري العرض...",
  "gm_encoding": "جاري ترميز GIF...",
  "gm_done": "تم!",
  "gm_fallback_encoder": "استخدام المشفر البديل...",
  "gm_lib_load_fail": "فشل تحميل مكتبة GIF.",
  "gm_lib_load_fail_alert": "تعذر تحميل مكتبة ترميز GIF. يرجى التحقق من الشبكة.",
  "ppt_tpl_title": "عنوان",
  "ppt_presentation_title": "عنوان العرض التقديمي",
  "ppt_enter_subtitle": "أدخل العنوان الفرعي",
  "ppt_tpl_title_body": "عنوان + نص",
  "ppt_slide_title": "عنوان الشريحة",
  "ppt_body_placeholder": "أدخل النص هنا.\nأضف النقاط الرئيسية والتفاصيل.",
  "ppt_tpl_two_col": "عمودان",
  "ppt_left_col": "أدخل محتوى العمود الأيسر.",
  "ppt_right_col": "أدخل محتوى العمود الأيمن.",
  "ppt_tpl_img_text": "صورة + نص",
  "ppt_drag_image": "اسحب صورة\nإلى هنا",
  "ppt_content_title": "عنوان المحتوى",
  "ppt_desc_placeholder": "أدخل نص الوصف. سيظهر بجانب الصورة.",
  "ppt_tpl_quote": "اقتباس",
  "ppt_quote_placeholder": "أدخل اقتباساً مؤثراً هنا.",
  "ppt_speaker_name": "- اسم المتحدث",
  "ppt_tpl_blank": "شريحة فارغة",
  "ppt_add_slide": "إضافة شريحة",
  "ppt_duplicate_slide": "تكرار الشريحة",
  "ppt_templates": "القوالب",
  "ppt_preview": "معاينة",
  "ppt_speaker_notes": "ملاحظات المتحدث",
  "ppt_notes_placeholder": "أدخل ملاحظات لهذه الشريحة...",
  "ppt_duplicate": "تكرار",
  "ppt_delete": "حذف",
  "ppt_delete_confirm": "حذف هذه الشريحة؟",
  "ppt_loading_slides": "جاري تحميل الشرائح...",
  "ppt_no_notes": "لا توجد ملاحظات لهذه الشريحة.",
  "ve_tab_media": "وسائط",
  "ve_tab_audio": "صوت",
  "ve_tab_text": "نص",
  "ve_tab_element": "عناصر",
  "ve_tab_image": "صورة",
  "ve_tab_transition": "انتقال",
  "ve_tab_adjust": "تعديل",
  "ve_tab_template": "قوالب",
  "ve_tab_save": "حفظ",
  "ve_download": "تحميل",
  "ve_properties": "الخصائص",
  "ve_ai_prompt_placeholder": "ما الحركة التي تريدها؟ (مثال: تكبير بطيء، شعر يتطاير مع الرياح...)",
  "ve_ai_generate": "فيديو AI",
  "ve_ai_generated_label": "هذا فيديو تم إنشاؤه بالذكاء الاصطناعي",
  "ve_ai_revert": "استعادة الصورة الأصلية",
  "ve_ai_status_generating": "جاري إنشاء فيديو AI...",
  "ve_ai_cancel": "إلغاء",
  "ve_drop_files": "أسقط الملفات هنا",
  "ve_ctx_front": "إلى الأمام",
  "ve_ctx_forward": "تقديم",
  "ve_ctx_backward": "تأخير",
  "ve_ctx_back": "إلى الخلف",
  "ve_ctx_copy": "نسخ",
  "ve_ctx_paste": "لصق",
  "ve_ctx_delete": "حذف",
  "ve_preparing": "جاري التحضير...",
  "ve_click_upload": "انقر لإضافة وسائط",
  "ve_drag_hint": "أو اسحب وأفلت الملفات",
  "ve_unlocked_short": "غير مقفل",
  "ve_audio_selected": "محدد",
  "ve_locked": "مقفل",
  "ve_unlocked": "غير مقفل",
  "ve_scale": "مقياس",
  "ve_reset_pos": "إعادة تعيين الموضع",
  "ve_generating": "جاري الإنشاء...",
  "ve_encoding": "جاري الترميز...",
  "ve_done": "تم!",
  "ve_make_video": "إنشاء فيديو",
  "ve_ai_uploading": "رفع الصورة...",
  "ve_ai_starting": "بدء AI...",
  "ve_ai_generating": "إنشاء فيديو AI...",
  "ve_ai_downloading": "تحميل الفيديو...",
  "ve_ai_done": "تم إنشاء فيديو AI!",
  "ve_ai_cancelled": "تم الإلغاء",
  "ve_ai_processing": "معالجة فيديو AI...",
  "ve_ai_queue_wait": "في قائمة انتظار AI...",
  "ve_ai_video_fail": "فشل إنشاء فيديو AI",
  "ve_ai_revert_confirm": "إزالة تأثيرات AI واستعادة الصورة الأصلية؟",
  "gm_title": "صانع GIF",
  "gm_canvas_size": "الحجم:",
  "gm_apply": "تطبيق",
  "gm_speed_label": "السرعة:",
  "gm_speed_fastest": "سريع جداً (0.1ث)",
  "gm_speed_fast": "سريع (0.2ث)",
  "gm_speed_normal": "عادي (0.5ث)",
  "gm_speed_slow": "بطيء (1ث)",
  "gm_speed_slowest": "بطيء جداً (2ث)",
  "gm_save_gif": "حفظ GIF",
  "gm_tab_frames": "إطارات",
  "gm_tab_text": "نص",
  "gm_tab_elements": "عناصر",
  "gm_tab_image": "صورة",
  "gm_upload_photos": "رفع صور (حد أقصى 10)",
  "gm_drag_hint": "اسحب لإعادة الترتيب<br>انقر لتحديد الإطار",
  "gm_add_text": "إضافة نص",
  "gm_font": "الخط",
  "gm_size": "الحجم",
  "gm_color": "اللون",
  "gm_outline": "الحدود",
  "gm_stickers": "ملصقات",
  "gm_place_sticker": "وضع ملصق على اللوحة",
  "gm_img_elements": "عناصر الصور",
  "gm_search_elements": "بحث عناصر...",
  "gm_loading": "جاري التحميل...",
  "gm_load_more": "تحميل المزيد",
  "gm_search_images": "بحث صور...",
  "ve_ai_photo_upload": "تأليف AI من صورة",
  "ve_ai_photo_desc": "يحلل AI الصورة وينشئ كلمات وأسلوب تلقائيًا",
  "ve_ai_photo_analyzing": "جاري تحليل الصورة...",
  "ve_ai_photo_done": "تم التحليل! انقر على Generate",
  "ve_ai_photo_fail": "فشل تحليل الصورة",
  "ve_bgm_title": "موسيقى خلفية",
  "ve_bgm_empty": "لا توجد موسيقى خلفية",
  "btn_3d_preview": "معاينة 3D",
  "modal_3d_title": "معاينة 3D",
  "hint_3d_controls": "🖱 سحب: تدوير | تمرير: تكبير | نقر يمين: تحريك",
  "btn_3d_refresh": "تحديث التصميم",
  "box_dimensions": "الصندوق (مم)",
  "box_face_front": "الأمام",
  "box_face_back": "الخلف",
  "box_face_left": "اليسار",
  "box_face_right": "اليمين",
  "box_face_top": "الأعلى",
  "box_face_bottom": "الأسفل",
  "pd_tab_ad": "إعلان علوي",
  "pd_tab_side": "لوحة جانبية",
  "pd_tab_shelf": "رف",
  "pd_tab_bottom": "أسفل",
  "box_apply": "تطبيق",
  "box_sheets": "ورقة",
  "box_download_layout": "مخطط التخطيط",
  "box_apply_first": "يرجى تطبيق أبعاد الصندوق أولاً",
  "box_too_large": "الوجه يتجاوز حجم اللوح (2400×1200مم)",
  "login_save_msg": "لحفظ تصاميمك،<br>يرجى التسجيل أو تسجيل الدخول.",
  "login_browse_guest": "تصفح بدون تسجيل",
  "placeholder_id": "اسم المستخدم (أو البريد)",
  "btn_quick_signup": "تسجيل سريع",
  "hero_signup_btn": "تسجيل في ثانية واحدة",
  "hero_signup_desc": "بدون تحقق. فقط أدخل اسم المستخدم وكلمة المرور وابدأ فوراً.",
  "signup_guide_title": "تسجيل فوري",
  "signup_guide_desc": "أدخل اسم المستخدم وكلمة المرور فقط<br>لا حاجة لبريد تأكيد!",
  "gm_upload_video": "استخراج إطارات من الفيديو",
  "ppt_export": "تصدير PPT",
  "ppt_trans_none": "بدون",
  "ppt_trans_fade": "تلاشي",
  "ppt_trans_slide": "انزلاق",
  "ppt_trans_zoom": "تكبير",
  "ppt_trans_wipe": "مسح",
  "ppt_trans_push": "دفع",
  "loading_product": "...جارٍ الانتقال إلى صفحة المنتج",
  "wall_preset_title": "الإعداد المسبق",
  "wall_face_front": "الأمام",
  "wall_face_back": "الخلف",
  "wall_add_btn": "إضافة جدار",
  "wall_delete_btn": "حذف",
  "wall_rotate_btn": "تدوير",
  "wall_preset_booth": "كشك",
  "wall_preset_square": "مربع",
  "msg_min_wall": "يلزم جدار واحد على الأقل",
  "hint_3d_wall_controls": "انقر: تحديد | Shift+سحب: نقل | سحب: تدوير",
  "wall_opt_label": "خيارات",
  "wall_opt_corner_pillar": "عمود زاوية",
  "wall_opt_top_light": "إضاءة علوية (أبيض)",
  "wall_opt_outdoor_stand": "حامل خارجي (مجموعة واحدة)",
  "wall_acc_light": "إضاءة",
  "wall_acc_stand": "حامل",
  "wall_acc_set_unit": "مجموعة",
  "btn_forgot_pw": "هل نسيت كلمة المرور؟",
  "modal_forgot_pw_title": "استعادة كلمة المرور",
  "msg_forgot_pw_desc": "أدخل عنوان بريدك الإلكتروني المسجل<br>وسنرسل لك رابط إعادة تعيين كلمة المرور.",
  "btn_send_reset_email": "إرسال رابط إعادة التعيين",
  "btn_back_to_login": "العودة لتسجيل الدخول",
  "modal_reset_pw_title": "إعادة تعيين كلمة المرور",
  "msg_reset_pw_desc": "يرجى إدخال كلمة المرور الجديدة.",
  "placeholder_new_pw": "كلمة المرور الجديدة (6 أحرف على الأقل)",
  "placeholder_new_pw_confirm": "تأكيد كلمة المرور الجديدة",
  "btn_change_pw": "تغيير كلمة المرور",
  "msg_reset_email_sent": "تم إرسال بريد إعادة التعيين. يرجى التحقق من صندوق الوارد.",
  "msg_pw_changed": "تم تغيير كلمة المرور بنجاح. يرجى تسجيل الدخول بكلمة المرور الجديدة.",
  "//_ICON_PANEL": "--- لوحة الأيقونات ---",
  "menu_icon": "أيقونات",
  "ph_search_icon": "بحث عن أيقونة (مثال: star, home)",
  "icon_color": "اللون",
  "icon_color_reset": "أصلي",
  "icon_load_more": "تحميل المزيد",
  "icon_no_results": "لا توجد نتائج",
  "icon_loading": "جاري البحث...",
  "tab_icons": "أيقونات",
  "tab_logos": "شعارات",
  "ph_search_logo": "بحث عن شعار (مثال: google, nike)",
  "//_PROMO_SUBSCRIPTION": "--- العروض/الاشتراك ---",
  "promo_banner_title": "خصم اشتراك 10% + خصم إحالة 10% + نقاط 5%<br>احصل على خصم يصل إلى 25%!",
  "promo_banner_desc": "اشترك الآن واحصل على مليون نقطة فوراً!<br>استخدم حتى 5% لكل عملية شراء",
  "promo_sub_rate": "10%",
  "promo_sub_label": "خصم الاشتراك",
  "promo_ref_rate": "10%",
  "promo_ref_label": "خصم الإحالة",
  "promo_mile_rate": "5%",
  "promo_mile_label": "استخدام النقاط",
  "promo_mileage_info": "احصل على <b style=\"color:#fbbf24;\">مليون نقطة</b> فور الاشتراك<br>استخدم حتى 5% من قيمة الطلب (ليست رصيداً نقدياً)",
  "promo_referral_info": "سجّل مع صديق كمُحيل<br><b style=\"color:#34d399;\">أنت تحصل على خصم 5%</b>، <b style=\"color:#fbbf24;\">صديقك يحصل على 5% نقداً!</b>",
  "promo_cta_btn": "اشترك واحصل على خصم 25% + مليون نقطة",
  "promo_big_sub": "اشتراك 10%",
  "promo_big_ref": "إحالة 10%",
  "promo_big_mile": "رصيد النقاط",
  "promo_big_total": "خصم 10% + رصيد الاشتراك",
  "sub_mileage_cta": "🎁 احصل على رصيد يعادل اشتراكك",
  "sub_feat_mileage": "مليون نقطة فورية",
  "sub_feat_referral": "خصم إحالة 5% · صديقك 5% نقداً",
  "//_DELIVERY_AREA": "--- منطقة التوصيل ---",
  "desc_delivery_area_kr": "ألواح Honeycomb Board تتطلب رسوم شحن إضافية خارج سيول/كيونغي.",
  "opt_metro_area": "منطقة العاصمة (سيول/كيونغي)",
  "opt_non_metro_area": "مناطق أخرى",
  "msg_non_metro_fee": "رسوم شحن إضافية للمناطق الأخرى: 200,000 وون.",
  "//_BUTTONS": "--- الأزرار ---",
  "btn_get_quote": "طلب عرض سعر مجاني",
  "btn_live_chat": "محادثة فورية",
  "btn_kakao_login": "تسجيل الدخول بكاكاو",
  "btn_download": "تحميل",
  "//_PDP_MOBILE": "--- تفاصيل المنتج/الجوال ---",
  "pdp_product_name": "اسم المنتج",
  "pdp_design_start": "🎨 صمم بنفسك",
  "pdp_file_upload": "📂 رفع ملف للطلب",
  "mobile_text_shapes": "نص وأشكال",
  "mobile_edit_align": "تحرير/محاذاة",
  "cat_select_size": "📏 يرجى اختيار الحجم (المنتج)",
  "//_CHAMELEON_CHAT": "--- الدردشة الذكية ---",
  "cham_title": "استشارة AI كاميليون",
  "cham_subtitle": "مساعد ذكي · متاح على مدار الساعة",
  "cham_new_chat": "محادثة جديدة",
  "cham_connect": "تواصل مع مستشار",
  "//_QUOTE_FORM": "--- نموذج عرض السعر ---",
  "quote_title": "طلب عرض سعر مجاني",
  "quote_subtitle": "استفسر بسهولة بدون تسجيل دخول",
  "quote_name": "الاسم / اسم الشركة",
  "quote_name_ph": "مثال: أحمد / شركة ABC",
  "quote_email_label": "البريد الإلكتروني *",
  "quote_phone": "رقم التواصل (اختياري)",
  "quote_phone_ph": "050-000-0000",
  "quote_detail": "تفاصيل الاستفسار *",
  "quote_detail_ph": "يرجى وصف المنتج المطلوب والكمية والحجم وموعد التسليم.",
  "quote_file": "مرفق (اختياري)",
  "quote_file_click": "انقر لاختيار ملف",
  "quote_submit": "إرسال طلب عرض السعر",
  "quote_alert_required": "يرجى إدخال البريد الإلكتروني وتفاصيل الاستفسار.",
  "quote_success": "تم إرسال طلب عرض السعر! سنرد عبر البريد الإلكتروني خلال 24 ساعة.",
  "quote_error": "فشل الإرسال. يرجى التواصل عبر الدردشة المباشرة.",
  "//_REFERRAL": "--- الإحالة ---",
  "label_referral_discount": "خصم الإحالة",
  "referral_thanks": "مُحيلك سيكون سعيداً. شكراً لك!",
  "referral_refund_notice": "في حال سحب المُحيل مبلغ المكافأة، سيتم خصمه من مبلغ الاسترداد.",
  "//_WALL_CONFIG": "--- إعداد الجدار ---",
  "wall_config_title": "إعداد حائط العرض",
  "wall_width": "العرض",
  "wall_sections": "الأقسام",
  "wall_custom_input": "إدخال مخصص",
  "wall_type": "النوع",
  "wall_single_sided": "وجه واحد",
  "wall_double_sided": "وجهين",
  "wall_count": "العدد",
  "wall_price_calc": "حساب السعر",
  "related_products": "منتجات مقترحة",
  "title_install_time": "🔧 اختيار وقت التركيب",
  "dsm_where_to_print": "على ماذا تريد الطباعة؟",
  "dsm_search_hint": "ابحث عما تريد صنعه",
  "dsm_search_examples": "مثال: لافتات، بطاقات عمل، ملصقات",
  "dsm_no_results": "لا توجد منتجات مطابقة.",
  "dsm_load_failed": "فشل في تحميل المنتجات",
  "dsm_size_error": "يرجى إدخال العرض والارتفاع بشكل صحيح.",
  "dsm_editor_error": "حدث خطأ أثناء تحميل المحرر.",
  "img_tool_replace": "استبدال",
  "menu_retouch": "تنقيح",
  "panel_retouch": "تنقيح الصور الشخصية",
  "retouch_select_image": "حدد صورة على اللوحة",
  "retouch_ai_title": "تنقيح AI للصور",
  "retouch_face": "تجميل البشرة",
  "retouch_blemish": "إزالة العيوب",
  "retouch_face_shape": "شكل الوجه",
  "retouch_full": "تجميل كامل",
  "retouch_manual_title": "ضبط يدوي",
  "retouch_brightness": "السطوع",
  "retouch_contrast": "التباين",
  "retouch_saturation": "التشبع",
  "retouch_warmth": "حرارة اللون",
  "retouch_sharpness": "الحدة",
  "retouch_blur": "ضبابية",
  "retouch_apply": "تطبيق",
  "retouch_reset": "إعادة تعيين",
  "retouch_presets_title": "فلاتر سريعة",
  "retouch_preset_portrait": "صورة شخصية",
  "retouch_preset_vivid": "حيوي",
  "retouch_preset_warm": "دافئ",
  "retouch_preset_cool": "بارد",
  "retouch_preset_bw": "أبيض وأسود",
  "retouch_preset_soft": "ناعم",
  "retouch_processing": "جاري التنقيح...",
  "retouch_done": "تم التنقيح!",
  "retouch_error": "فشل التنقيح",
  "retouch_undo": "تراجع",
  "retouch_original": "استعادة الأصل",
  "retouch_sec_beauty": "AI جمال",
  "retouch_sec_transform": "AI تحويل",
  "retouch_sec_magic": "تحرير سحري بالذكاء الاصطناعي",
  "retouch_magic_desc": "ارسم منطقة بالفرشاة، ثم احذفها أو استبدلها بمحتوى آخر.",
  "retouch_magic_brush": "فرشاة",
  "retouch_magic_clear": "مسح",
  "retouch_magic_size": "الحجم",
  "retouch_magic_prompt_ph": "استبدال بـ... (اتركه فارغاً للحذف)",
  "retouch_magic_apply": "تطبيق AI",
  "retouch_magic_brush_on": "وضع الفرشاة مفعّل — ارسم المنطقة",
  "retouch_magic_cleared": "تم مسح القناع",
  "retouch_magic_brush_first": "ارسم منطقة بالفرشاة أولاً",
  "retouch_magic_done": "اكتمل التحرير السحري بالذكاء الاصطناعي!",
  "retouch_sec_manual": "تعديل يدوي",
  "retouch_sec_presets": "فلتر سريع",
  "rt_smart_beauty": "جمال بنقرة",
  "rt_face_beauty": "تجميل البشرة",
  "rt_smart_skin": "إزالة الشوائب",
  "rt_enhancer": "تحسين الوجه",
  "rt_slimming": "تنحيف الوجه",
  "rt_skin_analysis": "تحليل البشرة",
  "rt_cartoon": "رسوم متحركة",
  "rt_emotion": "تعبيرات",
  "rt_age_gender": "العمر/الجنس",
  "rt_face_filter": "فلتر الوجه",
  "rt_hairstyle": "تسريحة الشعر",
  "rt_lips_color": "لون الشفاه",
  "rt_face_blur": "تمويه الوجه",
  "rt_face_fusion": "دمج الوجه",
  "retouch_cancel": "إلغاء",
  "opt_title_cartoon": "اختر نمط الرسوم",
  "opt_title_emotion": "اختر التعبير",
  "opt_title_age": "اختر نوع التحويل",
  "opt_title_filter": "اختر فلتر الوجه",
  "opt_title_hair": "اختر تسريحة الشعر",
  "opt_title_lips": "اختر لون الشفاه",
  "opt_title_fusion": "اختر صورة الوجه للدمج",
  "opt_3d_cartoon": "3D Cartoon",
  "opt_pixar": "Pixar",
  "opt_pixar_plus": "Pixar+",
  "opt_anime": "Anime",
  "opt_jpcartoon": "JP Cartoon",
  "opt_comic": "Comic",
  "opt_sketch": "Sketch",
  "opt_handdrawn": "Hand Drawn",
  "opt_3d_doll": "3D Doll",
  "opt_3d_game": "3D Game",
  "opt_angel": "Angel",
  "opt_demon": "Demon",
  "opt_artstyle": "Art",
  "opt_animation3d": "3D Animation",
  "opt_classic_cartoon": "Classic Cartoon",
  "opt_hongkong": "HK Style",
  "opt_dimple_smile": "Dimple Smile",
  "opt_belly_dimple": "Belly Dimple",
  "opt_big_smile": "Big Smile",
  "opt_hearty_laugh": "Hearty Laugh",
  "opt_cool_pose": "Cool Pose",
  "opt_sad": "Sad",
  "opt_forced_smile": "Forced Smile",
  "opt_open_eyes": "Open Eyes",
  "opt_to_kid": "To Child",
  "opt_to_old": "To Elder",
  "opt_to_female": "To Female",
  "opt_to_male": "To Male",
  "opt_natural": "Natural",
  "opt_whitening": "Whitening",
  "opt_pink": "Pink",
  "opt_elegant": "Elegant",
  "opt_youth": "Youth",
  "opt_retro": "Retro",
  "opt_cinema": "Cinema",
  "opt_vintage": "Vintage",
  "opt_warm_tone": "Warm Tone",
  "opt_cool_tone": "Cool Tone",
  "opt_dramatic": "Dramatic",
  "opt_monochrome": "Monochrome",
  "opt_neon": "Neon",
  "opt_sunset": "Sunset",
  "opt_bobcut": "Bob Cut",
  "opt_long_straight": "Long Straight",
  "opt_long_wavy": "Long Wavy",
  "opt_long_curly": "Long Curly",
  "opt_pixie": "Pixie Cut",
  "opt_curly_bob": "Curly Bob",
  "opt_ponytail": "Ponytail",
  "opt_updo": "Updo",
  "opt_chignon": "Chignon",
  "opt_fishtail": "Fishtail",
  "opt_twin_braids": "Twin Braids",
  "opt_shaved_sides": "Shaved Sides",
  "opt_double_bun": "Double Bun",
  "opt_dreadlocks": "Dreadlocks",
  "opt_shoulder": "Shoulder Length",
  "opt_box_braids": "Box Braids",
  "opt_buzzcut": "Buzz Cut",
  "opt_undercut": "Undercut",
  "opt_pompadour": "Pompadour",
  "opt_slickback": "Slick Back",
  "opt_curly_shag": "Curly Shag",
  "opt_wavy_shag": "Wavy Shag",
  "opt_fauxhawk": "Faux Hawk",
  "opt_twoblock": "Two Block",
  "opt_manbun": "Man Bun",
  "opt_combover": "Comb Over",
  "opt_afro": "Afro",
  "opt_cornrow": "Cornrow",
  "opt_red": "Red",
  "opt_rose": "Rose",
  "opt_coral": "Coral",
  "opt_berry": "Berry",
  "opt_wine": "Wine",
  "opt_nude_pink": "Nude Pink",
  "opt_deep_red": "Deep Red",
  "opt_hot_pink": "Hot Pink",
  "dsm_design_size": "أحجام التصميم",
  "dsm_a4_portrait": "A4 عمودي",
  "dsm_landscape": "أفقي",
  "dsm_square": "مربع",
  "dsm_banner_type": "بانر",
  "dsm_retouch": "تعديل الصور",
  "dsm_custom": "مخصص",
  "dsm_custom_desc": "إدخال الحجم",
  "dsm_custom_start": "ابدأ التصميم",
  "dsm_width": "العرض",
  "dsm_height": "الارتفاع",
  "dsm_size_min": "الحد الأدنى: 10 ملم",
  "biz_tpl_title": "اختر تصميم بطاقة العمل",
  "biz_tpl_desc": "اختر قالبًا وعدّل النص فقط لإنشاء بطاقة عملك.",
  "biz_tpl_classic": "كلاسيكي",
  "biz_tpl_modern": "عصري",
  "biz_tpl_minimal": "بسيط",
  "biz_tpl_colorblock": "كتلة لونية",
  "biz_tpl_vert_classic": "عمودي كلاسيكي",
  "biz_tpl_vert_color": "عمودي ملون",
  "biz_tpl_blank": "ابدأ بلوحة فارغة",
  "biz_ph_company": "طباعة كاميليون",
  "biz_ph_slogan": "Creative Design Solution",
  "biz_ph_name": "أحمد محمد",
  "biz_ph_title": "مدير / فريق التصميم",
  "biz_ph_title_short": "مدير",
  "biz_ph_phone": "+966-12-345-6789",
  "biz_ph_email": "hello@example.com",
  "biz_ph_address": "الرياض، شارع الملك فهد 123",
  "editor_gradient_palette": "تدرج لوني",
  "editor_text_label": "نص",
  "tab_ornaments": "زخارف",
  "ph_zip": "الرمز البريدي",
  "ph_state": "المنطقة/المحافظة",
  "ph_city": "المدينة",
  "ph_street1": "العنوان",
  "ph_street2": "شقة، جناح، وحدة (اختياري)",
  "wizard_label_body": "النص الأساسي",
  "wizard_body_placeholder": "مثال: قهوة طازجة يومياً، فنجان هادئ في أجواء مريحة",
  "close": "إغلاق",
  "no_uploaded_images": "لا توجد صور مرفوعة",
  "promo_remaining": "متبقي",
  "promo_offer": "اشتراك مجاني لمدة 3 أشهر للأعضاء الجدد!",
  "promo_mileage": "+ $100 رصيد متجر",
  "hero_desc_event": "ابدأ مجاناً",
  "promo_line1": "اشتراك مجاني 3 أشهر",
  "promo_line2": "+ $100 رصيد متجر",
  "promo_line3": "خصم 10% على جميع المنتجات",
  "trust_design_print": "تصميم وطباعة",
  "trust_design_print_sub": "صمم أونلاين، اطلب الطباعة مباشرة",
  "trust_secure": "دفع آمن",
  "trust_secure_sub": "Stripe وتشفير SSL",
  "trust_shipping": "شحن عالمي",
  "trust_shipping_sub": "توصيل لجميع أنحاء العالم",
  "badge_product": "منتج",
  "auth_terms_notice": "بالتسجيل، فإنك توافق على <a href='/terms.html' target='_blank' style='color:#6366f1; text-decoration:underline;'>شروط الخدمة</a> و<a href='/privacy.html' target='_blank' style='color:#6366f1; text-decoration:underline;'>سياسة الخصوصية</a>.",
  "mp_sub_title": "مشترك",
  "mp_sub_remaining": "متبقي",
  "mp_sub_expires": "ينتهي",
  "mp_sub_discount": "خصم",
  "mp_sub_discount_val": "خصم 10% على جميع المنتجات",
  "mp_sub_days": " يوم",
  "mp_sub_active": "نشط",
  "btn_line_login": "تسجيل الدخول بـ LINE",
  "promo_tpl_title": "اختيار تنسيق الطباعة",
  "promo_fmt_desc": "اختر تنسيق المطبوعة.",
  "promo_p_flyer1": "منشور A4",
  "promo_p_flyer1_d": "وجه واحد · 210×297mm",
  "promo_p_flyer2": "منشور A4 وجهين",
  "promo_p_flyer2_d": "وجهين · 210×297mm",
  "promo_p_postcard": "بطاقة بريدية",
  "promo_p_postcard_d": "وجهين · 100×148mm",
  "promo_p_invite": "دعوة",
  "promo_p_invite_d": "طي نصفي · 190×130mm",
  "promo_p_half": "A4 طي نصفي",
  "promo_p_half_d": "4 صفحات · 303×216mm",
  "promo_p_tri": "منشور ثلاثي الطي",
  "promo_p_tri_d": "6 صفحات · 303×216mm",
  "promo_front": "الأمام",
  "promo_back_label": "الخلف",
  "promo_fmt_single": "وجه واحد (1 صفحة)",
  "promo_fmt_single_desc": "منشورات، ملصقات",
  "promo_fmt_double": "وجهين (2 صفحة)",
  "promo_fmt_double_desc": "منشورات وجهين، بطاقات",
  "promo_fmt_half_fold": "طي نصفي (4 صفحات)",
  "promo_fmt_half_fold_desc": "قوائم، دعوات",
  "promo_fmt_tri_fold": "طي ثلاثي (6 صفحات)",
  "promo_fmt_tri_fold_desc": "كتيبات، مطويات",
  "promo_size_title": "حجم الورق",
  "promo_orient_v": "عمودي",
  "promo_orient_h": "أفقي",
  "promo_back": "رجوع",
  "promo_confirm_title": "تأكيد التنسيق",
  "promo_confirm": "ابدأ",
  "promo_face_front": "الأمام",
  "promo_face_back": "الخلف",
  "promo_pos_left": "يسار",
  "promo_pos_center": "وسط",
  "promo_pos_right": "يمين",
  "promo_tpl_company": "اسم الشركة",
  "promo_tpl_tagline": "شعارك هنا",
  "promo_tpl_map": "الموقع / الخريطة",
  "promo_tpl_address": "تفاصيل العنوان هنا",
  "promo_tpl_about": "من نحن",
  "promo_tpl_about_desc": "اكتب مقدمة موجزة عن شركتك أو خدمتك.",
  "promo_tpl_section": "قسم",
  "promo_tpl_lorem": "أضف محتواك هنا. صف الخدمات أو المنتجات التي تريد إبرازها.",
  "artwork_badge": "سوق الأعمال الفنية",
  "artwork_title": "بيع أعمالك الفنية",
  "artwork_revenue": "💰 اربح 10% من كل عملية بيع<br>🌍 يُباع في 20 دولة",
  "artwork_desc": "ارفع صورك أو رسوماتك وبيعها كـ <b style='color:#fff;'>8 أنواع منتجات</b>.",
  "artwork_copyright": "⚠️ مسؤولية حقوق النشر تقع على عاتق البائع الذي رفع العمل.",
  "artwork_upload_btn": "رفع عمل فني",
  "artwork_paper": "ملصق ورقي",
  "artwork_paper_unit": "للقطعة (A3)",
  "artwork_fabric": "ملصق قماشي",
  "artwork_fabric_unit": "للقطعة (A3)",
  "artwork_canvas": "إطار كانفاس",
  "artwork_canvas_unit": "للقطعة (A3)",
  "artwork_modal_title": "🎨 تسجيل عمل فني",
  "artwork_modal_desc": "عند رفع الصورة، سيتم تسجيلها تلقائياً كـ 3 منتجات (ملصق ورقي، ملصق قماشي، إطار كانفاس).",
  "artwork_label_image": "صورة العمل الفني",
  "artwork_label_title": "اسم العمل (كلمات البحث)",
  "artwork_ph_title": "مثال: مناظر طبيعية، فن تجريدي، رسوم قطط",
  "artwork_submit": "تسجيل العمل الفني",
  "artwork_close": "إغلاق",
  "artwork_label_calc": "💰 حاسبة الأسعار",
  "artwork_width": "العرض (mm)",
  "artwork_height": "الارتفاع (mm)",
  "artwork_auto_size": "حساب تلقائي",
  "label_artwork_revenue": "إيرادات العمل الفني",
  "label_contributor_reward": "مكافأة المساهم",
  "dsm_greeting_card": "بطاقة تهنئة",
  "gc_wizard_title": "إنشاء بطاقة تهنئة",
  "gc_category": "نوع المناسبة",
  "gc_cat_christmas": "عيد الميلاد",
  "gc_cat_newyear": "رأس السنة",
  "gc_cat_birthday": "عيد ميلاد",
  "gc_cat_thankyou": "شكر",
  "gc_cat_congrats": "تهنئة",
  "gc_cat_valentines": "عيد الحب",
  "gc_from": "من",
  "gc_to": "إلى",
  "gc_message": "الرسالة",
  "gc_animation": "تأثير الحركة",
  "gc_anim_snow": "ثلج",
  "gc_anim_confetti": "قصاصات",
  "gc_anim_sparkle": "بريق",
  "gc_anim_hearts": "قلوب",
  "gc_anim_fireworks": "ألعاب نارية",
  "gc_anim_none": "بدون",
  "gc_photos": "تحميل صور (حد أقصى 5)",
  "gc_photo_drop": "انقر لتحميل الصور",
  "gc_generate": "إنشاء البطاقة",
  "gc_generating": "جارٍ إنشاء البطاقة...",
  "gc_share": "مشاركة",
  "gc_share_title": "مشاركة البطاقة",
  "gc_share_saving": "جاري الحفظ...",
  "gc_share_url": "رابط المشاركة",
  "gc_share_copy": "نسخ",
  "gc_share_copied": "تم النسخ!",
  "gc_preview": "معاينة",
  "gc_add_page": "إضافة",
  "gc_duplicate": "تكرار",
  "gc_templates": "أقسام",
  "gc_section_templates": "قوالب الأقسام",
  "gc_tpl_replace_note": "سيتم استبدال محتوى الصفحة الحالية",
  "gc_pages": "الصفحات",
  "gc_delete_confirm": "هل تريد حذف هذه الصفحة؟",
  "menu_col_name": "اسم القائمة",
  "menu_col_price": "السعر",
  "menu_item": "قائمة",
  "menu_add_row": "إضافة صف",
  "menu_help_text": "بعد إنشاء القائمة، قم بتغيير الحجم على اللوحة لضبط التخطيط تلقائيًا.",
  "menu_edit_done": "تم التعديل",
  "menu_create": "إنشاء القائمة",
  "msg_object_locked": "تم قفل الكائن",
  "msg_object_unlocked": "تم إلغاء قفل الكائن",
  "min_order_notice": "طباعة كاميليون متجر جملة. الحد الأدنى للطلب 10,000 وون. نعدكم بأعلى جودة وأقل الأسعار.",
  "coupon_first_label": "🎉 أول شراء فقط",
  "coupon_first_title": "كوبون 30,000 وون مجاني",
  "coupon_first_desc": "حتى 30,000 وون مجانًا في طلبك الأول!",
  "coupon_hc_label": "🏗️ عرض خاص لألواح العسل",
  "coupon_hc_title": "إنتاج كشك مجاني",
  "coupon_hc_desc": "إنتاج + شحن + تركيب مجاني",
  "coupon_detail_btn": "اعرف المزيد →",
  "order_tracker_title": "حالة الطلب",
  "ot_customer": "اسم العميل",
  "ot_order_date": "تاريخ الطلب",
  "ot_ship_date": "تاريخ الشحن",
  "ot_photo": "الصور",
  "ot_inquiry": "استفسار",
  "ot_reply": "الرد",
  "ot_rating": "التقييم",
  "ot_progress": "التقدم",
  "ot_status": "الحالة",
  "ot_search_placeholder": "الاسم / رقم الاتصال",
  "ot_search_btn": "بحث",
  "ot_inquiry_review": "استفسار · تقييم",
  "ot_reply_thanks": "رد · شكراً",
  "ot_status_production_done": "اكتملت الإنتاج",
  "ot_status_received": "تم الاستلام",
  "ot_h_name": "اسم العميل",
  "ot_h_order": "تاريخ الطلب",
  "ot_h_ship": "تاريخ الشحن",
  "ot_h_photo": "الصور",
  "ot_h_inquiry": "استفسار",
  "ot_h_reply": "الرد",
  "ot_h_rating": "التقييم",
  "ot_h_progress": "التقدم",
  "ot_h_status": "الحالة",
  "ot_btn_inquiry_pc": "استفسار·تقييم",
  "ot_btn_inquiry_mb": "استفسار",
  "ot_btn_reply_pc": "رد·شكر",
  "ot_btn_reply_mb": "رد",
  "ot_st_접수됨": "تم الاستلام",
  "ot_st_칼선작업": "قص",
  "ot_st_제작중": "طباعة",
  "ot_st_완료됨": "مكتمل",
  "ot_st_발송완료": "شحن",
  "ot_st_배송완료": "تم التسليم",
  "order_tracker_search_placeholder": "الاسم/الاتصال",
  "ot_search_btn_text": "بحث",
  "ot_btn_search": "بحث",
  "rv_worldwide": "مشاهدة تقييمات الأصدقاء حول العالم",
  "rv_write_review": "كتابة تقييم",
  "rv_show_work": "عرض عملك",
  "rv_nickname_ph": "الاسم المستعار",
  "rv_nickname_required": "يرجى إدخال اسم مستعار",
  "home_wholesale_board_title": "ألواح قرص العسل الخام",
  "home_wholesale_board_desc": "نوفر ألواح قرص العسل الخام بأسعار الجملة"
}